{"y":"count","dates":["09\/19\/2022"],"series":[{"name":"Mini Pep Ito","id":"111679345","values":{"Squads":[20],"G10+":[100],"Def":[9],"G12+":[77],"G13+":[66],"7*":[208],"Zetas":[100],"Off":[10]}},{"name":"DaPandaMonster","id":"116152285","values":{"Squads":[17],"G10+":[105],"Def":[8],"G12+":[74],"G13+":[62],"7*":[208],"Zetas":[101],"Off":[8]}},{"name":"ilkori","id":"126853267","values":{"Squads":[17],"G10+":[98],"Def":[7],"G12+":[71],"G13+":[57],"7*":[227],"Zetas":[101],"Off":[7]}},{"name":"Chief64","id":"134866264","values":{"Squads":[21],"G10+":[147],"Def":[10],"G12+":[116],"G13+":[80],"7*":[216],"Zetas":[151],"Off":[8]}},{"name":"Bada Bing","id":"142215331","values":{"Squads":[16],"G10+":[79],"Def":[11],"G12+":[53],"G13+":[30],"7*":[204],"Zetas":[52],"Off":[8]}},{"name":"Seba","id":"173661396","values":{"Squads":[21],"G10+":[132],"Def":[10],"G12+":[110],"G13+":[94],"7*":[240],"Zetas":[166],"Off":[10]}},{"name":"Wogb","id":"228156277","values":{"Squads":[17],"G10+":[97],"Def":[9],"G12+":[80],"G13+":[68],"7*":[247],"Zetas":[110],"Off":[8]}},{"name":"BearlyAgang","id":"233924528","values":{"Squads":[21],"G10+":[106],"Def":[8],"G12+":[87],"G13+":[75],"7*":[206],"Zetas":[117],"Off":[10]}},{"name":"MINI Dace Joy","id":"269432561","values":{"Squads":[13],"G10+":[89],"Def":[8],"G12+":[82],"G13+":[69],"7*":[169],"Zetas":[81],"Off":[4]}},{"name":"Veleran Separ","id":"318952656","values":{"Squads":[19],"G10+":[135],"Def":[8],"G12+":[116],"G13+":[94],"7*":[216],"Zetas":[88],"Off":[7]}},{"name":"MINI DarthNynjur","id":"343154976","values":{"Squads":[18],"G10+":[105],"Def":[7],"G12+":[92],"G13+":[79],"7*":[242],"Zetas":[129],"Off":[8]}},{"name":"Filips chickens V2","id":"354119441","values":{"Squads":[19],"G10+":[99],"Def":[10],"G12+":[72],"7*":[209],"G13+":[55],"Zetas":[109],"Off":[8]}},{"name":"Tersor Ormageddon","id":"362575677","values":{"Squads":[20],"G10+":[108],"Def":[9],"G12+":[84],"7*":[266],"G13+":[63],"Zetas":[134],"Off":[8]}},{"name":"Ronons Force Ghost","id":"381858365","values":{"Squads":[11],"G10+":[101],"Def":[5],"G12+":[68],"G13+":[60],"7*":[144],"Zetas":[106],"Off":[5]}},{"name":"I Grimnar I","id":"394622541","values":{"Squads":[13],"G10+":[78],"Def":[7],"G12+":[65],"G13+":[48],"7*":[204],"Zetas":[76],"Off":[5]}},{"name":"Sparhawk Levaron","id":"395234187","values":{"Squads":[15],"G10+":[88],"Def":[6],"G12+":[75],"7*":[179],"G13+":[61],"Zetas":[93],"Off":[5]}},{"name":"Chalupa Jr","id":"456638194","values":{"Squads":[17],"G10+":[95],"Def":[7],"G12+":[84],"G13+":[72],"7*":[188],"Zetas":[114],"Off":[6]}},{"name":"iddqd7331","id":"473332458","values":{"Squads":[20],"G10+":[107],"Def":[8],"G12+":[89],"7*":[197],"G13+":[61],"Zetas":[112],"Off":[8]}},{"name":"MINI TheOneTruePretzel","id":"528442299","values":{"Squads":[14],"G10+":[98],"Def":[7],"G12+":[77],"G13+":[64],"7*":[223],"Zetas":[97],"Off":[7]}},{"name":"SepticSugar","id":"531439773","values":{"Squads":[13],"G10+":[66],"Def":[9],"G12+":[47],"7*":[156],"G13+":[40],"Zetas":[64],"Off":[6]}},{"name":"Velusiia","id":"541224862","values":{"Squads":[15],"G10+":[95],"Def":[9],"G12+":[74],"7*":[174],"G13+":[59],"Zetas":[104],"Off":[7]}},{"name":"Dizzle","id":"566511783","values":{"Squads":[24],"G10+":[137],"Def":[11],"G12+":[115],"7*":[270],"G13+":[101],"Zetas":[140],"Off":[12]}},{"name":"Brooks","id":"596812136","values":{"Squads":[16],"G10+":[75],"Def":[7],"G12+":[66],"G13+":[54],"7*":[193],"Zetas":[83],"Off":[7]}},{"name":"AquaRex","id":"613226156","values":{"Squads":[12],"G10+":[76],"Def":[6],"G12+":[52],"G13+":[41],"7*":[131],"Zetas":[69],"Off":[7]}},{"name":"Auzbeast","id":"637396872","values":{"Squads":[20],"G10+":[129],"Def":[7],"G12+":[92],"G13+":[80],"7*":[222],"Zetas":[143],"Off":[7]}},{"name":"MINI Ruibarian","id":"642573143","values":{"Squads":[17],"G10+":[91],"Def":[8],"G12+":[84],"G13+":[66],"7*":[215],"Zetas":[96],"Off":[7]}},{"name":"snake","id":"647855275","values":{"Squads":[20],"G10+":[108],"Def":[12],"G12+":[94],"G13+":[77],"7*":[213],"Zetas":[138],"Off":[9]}},{"name":"Peregine","id":"649766578","values":{"Squads":[19],"G10+":[112],"Def":[9],"G12+":[91],"G13+":[78],"7*":[234],"Zetas":[136],"Off":[10]}},{"name":"Aceblade","id":"671271358","values":{"Squads":[20],"G10+":[90],"Def":[12],"G12+":[57],"G13+":[39],"7*":[184],"Zetas":[117],"Off":[8]}},{"name":"ManiacalVampire","id":"678136272","values":{"Squads":[13],"G10+":[76],"Def":[6],"G12+":[59],"G13+":[49],"7*":[155],"Zetas":[82],"Off":[5]}},{"name":"Defiant","id":"771977741","values":{"Squads":[22],"G10+":[144],"Def":[9],"G12+":[124],"G13+":[103],"7*":[247],"Zetas":[130],"Off":[11]}},{"name":"Uzichow","id":"787311459","values":{"Squads":[21],"G10+":[137],"Def":[9],"G12+":[109],"G13+":[85],"7*":[221],"Zetas":[159],"Off":[9]}},{"name":"Monkeyisbest","id":"793493441","values":{"Squads":[16],"G10+":[89],"Def":[8],"G12+":[70],"G13+":[60],"7*":[231],"Zetas":[93],"Off":[9]}},{"name":"Winzorg","id":"793632989","values":{"Squads":[12],"G10+":[64],"Def":[7],"G12+":[50],"7*":[197],"G13+":[40],"Zetas":[55],"Off":[6]}},{"name":"Granite Fox","id":"812363892","values":{"Squads":[17],"G10+":[97],"Def":[9],"G12+":[84],"G13+":[75],"7*":[260],"Zetas":[106],"Off":[7]}},{"name":"WizenSlinky","id":"827524916","values":{"Squads":[21],"G10+":[115],"Def":[7],"G12+":[96],"G13+":[75],"7*":[238],"Zetas":[114],"Off":[10]}},{"name":"GeorgeyBoy","id":"838172774","values":{"Squads":[19],"G10+":[127],"Def":[7],"G12+":[105],"G13+":[75],"7*":[224],"Zetas":[126],"Off":[8]}},{"name":"Cidestep","id":"839898512","values":{"Squads":[21],"G10+":[139],"Def":[9],"G12+":[106],"G13+":[83],"7*":[216],"Zetas":[150],"Off":[8]}},{"name":"Bespin Skywalking","id":"846525532","values":{"Squads":[13],"G10+":[96],"Def":[5],"G12+":[71],"G13+":[59],"7*":[176],"Zetas":[84],"Off":[6]}},{"name":"Phobos","id":"848671248","values":{"Squads":[22],"G10+":[136],"Def":[8],"G12+":[109],"G13+":[85],"7*":[251],"Zetas":[159],"Off":[8]}},{"name":"Awakened","id":"855626143","values":{"Squads":[20],"G10+":[142],"Def":[9],"G12+":[112],"G13+":[91],"7*":[253],"Zetas":[137],"Off":[8]}},{"name":"Agangofbears","id":"866558338","values":{"Squads":[22],"G10+":[132],"Def":[6],"G12+":[118],"G13+":[101],"7*":[234],"Zetas":[155],"Off":[7]}},{"name":"SirPanda","id":"868699295","values":{"Squads":[14],"G10+":[73],"Def":[8],"G12+":[57],"G13+":[48],"7*":[189],"Zetas":[98],"Off":[4]}},{"name":"Babadook","id":"882439211","values":{"Squads":[19],"G10+":[92],"Def":[11],"G12+":[75],"7*":[218],"G13+":[59],"Zetas":[100],"Off":[9]}},{"name":"C3P0","id":"884979616","values":{"Squads":[18],"G10+":[122],"Def":[9],"G12+":[90],"7*":[232],"G13+":[60],"Zetas":[126],"Off":[5]}},{"name":"ŤUSK","id":"886366465","values":{"Squads":[18],"G10+":[80],"Def":[9],"G12+":[59],"G13+":[49],"7*":[171],"Zetas":[69],"Off":[9]}},{"name":"Laserbeak","id":"912151483","values":{"Squads":[24],"G10+":[166],"Def":[9],"G12+":[150],"G13+":[98],"7*":[241],"Zetas":[182],"Off":[10]}},{"name":"Lizsen Kendet","id":"946189996","values":{"Squads":[19],"G10+":[115],"Def":[9],"G12+":[91],"7*":[193],"G13+":[76],"Zetas":[109],"Off":[7]}}]}