{"y":"gp","dates":["09\/19\/2022"],"series":[{"name":"Mini Pep Ito","id":"111679345","values":{"FO":[58488],"Troopers":[125000],"zEP":[142737],"Traya":[77650],"SLKR":[-1],"NS":[95839],"Special":[29401],"Chimaera+Bugs":[368587],"Dooku+Sep":[-1],"Dooku+Asajj":[52535],"Chimaera":[136862],"Executrix":[298557],"Nute":[130104],"Poggle Geos":[107062],"Geos-Special":[107062],"NS-NoAssaj":[-1],"DR":[-1],"Geos":[107062],"BH":[143417],"SEE":[-1],"Grievous":[137017]}},{"name":"DaPandaMonster","id":"116152285","values":{"FO":[-1],"Troopers":[111480],"zEP":[148901],"Traya":[109116],"SLKR":[152254],"NS":[76472],"Special":[-1],"Chimaera+Bugs":[352249],"Dooku+Sep":[-1],"Dooku+Asajj":[45861],"Chimaera":[143267],"Executrix":[246567],"Nute":[114884],"Poggle Geos":[83425],"Geos-Special":[83425],"DR":[126277],"NS-NoAssaj":[69068],"Geos":[83425],"BH":[140125],"SEE":[-1],"Grievous":[127073]}},{"name":"ilkori","id":"126853267","values":{"FO":[77816],"zEP":[131430],"Troopers":[108680],"Traya":[70548],"SLKR":[-1],"NS":[96094],"Special":[29029],"Chimaera+Bugs":[344744],"Dooku+Sep":[-1],"Dooku+Asajj":[42417],"Chimaera":[118357],"Executrix":[263783],"Nute":[106767],"Poggle Geos":[101702],"Geos-Special":[101702],"DR":[110943],"NS-NoAssaj":[-1],"Geos":[101702],"BH":[143868],"SEE":[-1],"Grievous":[119930]}},{"name":"Chief64","id":"134866264","values":{"FO":[-1],"Troopers":[126425],"zEP":[146724],"Traya":[109851],"SLKR":[152861],"NS":[103305],"Special":[20329],"Chimaera+Bugs":[374324],"Dooku+Sep":[-1],"Dooku+Asajj":[42903],"Chimaera":[140444],"Executrix":[276589],"Nute":[118430],"Poggle Geos":[104184],"Geos-Special":[104184],"DR":[137521],"NS-NoAssaj":[-1],"Geos":[104184],"BH":[134921],"SEE":[-1],"Grievous":[130205]}},{"name":"Bada Bing","id":"142215331","values":{"FO":[72071],"Troopers":[59175],"zEP":[102611],"Traya":[63642],"SLKR":[-1],"NS":[71490],"Special":[16842],"Dooku+Asajj":[37321],"Dooku+Sep":[-1],"Chimaera+Bugs":[279700],"Chimaera":[92056],"Executrix":[224494],"Nute":[116744],"Poggle Geos":[99190],"Geos-Special":[99190],"DR":[119846],"NS-NoAssaj":[-1],"Geos":[99190],"BH":[107748],"SEE":[-1],"Grievous":[127876]}},{"name":"Seba","id":"173661396","values":{"FO":[-1],"Troopers":[96599],"zEP":[145095],"Traya":[94049],"SLKR":[154556],"NS":[109917],"Special":[29122],"Dooku+Asajj":[60110],"Dooku+Sep":[-1],"Chimaera+Bugs":[351183],"Chimaera":[128103],"Executrix":[289284],"Nute":[131838],"Poggle Geos":[103071],"Geos-Special":[103071],"DR":[140740],"NS-NoAssaj":[-1],"Geos":[103071],"BH":[146629],"SEE":[-1],"Grievous":[134403]}},{"name":"Wogb","id":"228156277","values":{"FO":[-1],"Troopers":[97535],"zEP":[141328],"Traya":[77780],"SLKR":[154260],"NS":[85835],"Special":[29385],"Dooku+Asajj":[33712],"Dooku+Sep":[-1],"Chimaera+Bugs":[340054],"Chimaera":[121842],"Executrix":[254462],"Nute":[107563],"Poggle Geos":[92684],"Geos-Special":[92684],"DR":[120051],"NS-NoAssaj":[77670],"Geos":[92684],"BH":[144267],"SEE":[-1],"Grievous":[123008]}},{"name":"BearlyAgang","id":"233924528","values":{"FO":[66555],"Troopers":[130697],"zEP":[156842],"Traya":[92973],"SLKR":[-1],"NS":[75650],"Special":[29340],"Dooku+Asajj":[43946],"Dooku+Sep":[-1],"Chimaera+Bugs":[382018],"Chimaera":[146446],"Executrix":[274980],"Nute":[111270],"Poggle Geos":[108828],"Geos-Special":[108828],"DR":[137901],"NS-NoAssaj":[-1],"Geos":[108828],"BH":[149263],"SEE":[-1],"Grievous":[124020]}},{"name":"MINI Dace Joy","id":"269432561","values":{"FO":[-1],"Troopers":[-1],"zEP":[140829],"Traya":[-1],"SLKR":[152591],"NS":[-1],"Special":[29007],"Dooku+Asajj":[48801],"Dooku+Sep":[-1],"Chimaera+Bugs":[325637],"Chimaera":[98731],"Executrix":[291862],"Nute":[122077],"Poggle Geos":[103004],"Geos-Special":[103004],"DR":[107670],"NS-NoAssaj":[-1],"Geos":[103004],"BH":[140988],"SEE":[-1],"Grievous":[134183]}},{"name":"Veleran Separ","id":"318952656","values":{"FO":[-1],"Troopers":[116462],"zEP":[138524],"Traya":[108782],"SLKR":[152712],"NS":[77635],"Special":[26088],"Dooku+Asajj":[55234],"Dooku+Sep":[-1],"Chimaera+Bugs":[330353],"Chimaera":[100348],"Executrix":[293194],"Nute":[124297],"Poggle Geos":[101679],"Geos-Special":[101679],"DR":[120641],"NS-NoAssaj":[-1],"Geos":[101679],"BH":[137869],"SEE":[-1],"Grievous":[133922]}},{"name":"MINI DarthNynjur","id":"343154976","values":{"FO":[124588],"Troopers":[134244],"zEP":[137135],"Traya":[120192],"SLKR":[-1],"NS":[83490],"Special":[-1],"Dooku+Asajj":[42964],"Dooku+Sep":[-1],"Chimaera+Bugs":[367043],"Chimaera":[132416],"Executrix":[281377],"Nute":[122167],"Poggle Geos":[101731],"Geos-Special":[101731],"DR":[135240],"NS-NoAssaj":[-1],"Geos":[101731],"BH":[145032],"SEE":[-1],"Grievous":[135262]}},{"name":"Filips chickens V2","id":"354119441","values":{"FO":[75392],"Troopers":[134073],"zEP":[-1],"Traya":[105439],"SLKR":[-1],"NS":[76271],"Special":[-1],"Dooku+Asajj":[51330],"Dooku+Sep":[-1],"Chimaera+Bugs":[367533],"Chimaera":[148973],"Executrix":[271831],"Nute":[115721],"Poggle Geos":[89570],"Geos-Special":[89570],"DR":[123850],"NS-NoAssaj":[-1],"Geos":[89570],"BH":[144879],"SEE":[170039],"Grievous":[128321]}},{"name":"Tersor Ormageddon","id":"362575677","values":{"FO":[89209],"Troopers":[112774],"zEP":[-1],"Traya":[88882],"SLKR":[-1],"NS":[121358],"Special":[-1],"Dooku+Asajj":[54860],"Dooku+Sep":[-1],"Chimaera+Bugs":[359562],"Chimaera":[143089],"Executrix":[271782],"Nute":[108029],"Poggle Geos":[98851],"Geos-Special":[98851],"DR":[137441],"NS-NoAssaj":[-1],"Geos":[98851],"BH":[144071],"SEE":[167310],"Grievous":[122878]}},{"name":"Ronons Force Ghost","id":"381858365","values":{"FO":[-1],"Troopers":[97281],"zEP":[140806],"Traya":[-1],"SLKR":[-1],"NS":[-1],"Special":[29146],"Dooku+Asajj":[41146],"Dooku+Sep":[-1],"Chimaera+Bugs":[308205],"Chimaera":[97021],"Executrix":[234315],"Nute":[110695],"Poggle Geos":[89414],"Geos-Special":[89414],"DR":[-1],"NS-NoAssaj":[-1],"Geos":[89414],"BH":[142542],"SEE":[-1],"Grievous":[123025]}},{"name":"I Grimnar I","id":"394622541","values":{"FO":[62007],"Troopers":[99590],"zEP":[146340],"Traya":[-1],"SLKR":[-1],"NS":[82242],"Special":[29077],"Dooku+Asajj":[40823],"Dooku+Sep":[-1],"Chimaera+Bugs":[304476],"Chimaera":[104875],"Executrix":[251507],"Nute":[107860],"Poggle Geos":[100880],"Geos-Special":[100880],"DR":[125366],"NS-NoAssaj":[71946],"Geos":[100880],"BH":[112300],"SEE":[-1],"Grievous":[121722]}},{"name":"Sparhawk Levaron","id":"395234187","values":{"FO":[66150],"Troopers":[89502],"zEP":[126100],"Traya":[-1],"SLKR":[-1],"NS":[72028],"Special":[28936],"Dooku+Asajj":[31582],"Chimaera+Bugs":[324357],"Dooku+Sep":[-1],"Chimaera":[107448],"Executrix":[245929],"Nute":[120286],"Poggle Geos":[100489],"Geos-Special":[100489],"NS-NoAssaj":[66101],"DR":[-1],"Geos":[100489],"BH":[139124],"SEE":[-1],"Grievous":[132104]}},{"name":"Chalupa Jr","id":"456638194","values":{"FO":[-1],"Troopers":[102071],"zEP":[-1],"Traya":[119495],"SLKR":[155356],"NS":[86121],"Special":[-1],"Dooku+Asajj":[48358],"Chimaera+Bugs":[363490],"Dooku+Sep":[-1],"Chimaera":[142001],"Executrix":[271644],"Nute":[120694],"Poggle Geos":[98917],"Geos-Special":[98917],"NS-NoAssaj":[-1],"DR":[-1],"Geos":[98917],"BH":[145246],"SEE":[175663],"Grievous":[132715]}},{"name":"iddqd7331","id":"473332458","values":{"FO":[65725],"Troopers":[117669],"zEP":[128351],"Traya":[87969],"SLKR":[-1],"NS":[100046],"Special":[29323],"Dooku+Asajj":[47606],"Chimaera+Bugs":[355238],"Dooku+Sep":[-1],"Chimaera":[132485],"Executrix":[263923],"Nute":[126334],"Poggle Geos":[94622],"Geos-Special":[94622],"NS-NoAssaj":[-1],"DR":[106545],"Geos":[94622],"BH":[148526],"SEE":[-1],"Grievous":[135182]}},{"name":"MINI TheOneTruePretzel","id":"528442299","values":{"FO":[73543],"Troopers":[76873],"zEP":[130614],"Traya":[89807],"SLKR":[-1],"NS":[81636],"Special":[28843],"Dooku+Asajj":[40317],"Chimaera+Bugs":[315731],"Dooku+Sep":[-1],"Chimaera":[100635],"Executrix":[257045],"Nute":[116565],"Poggle Geos":[109089],"Geos-Special":[109089],"NS-NoAssaj":[76371],"DR":[115416],"Geos":[109089],"BH":[112907],"SEE":[-1],"Grievous":[128945]}},{"name":"SepticSugar","id":"531439773","values":{"FO":[55528],"Troopers":[93890],"zEP":[125464],"Traya":[-1],"SLKR":[-1],"NS":[80721],"Special":[17269],"Dooku+Asajj":[33755],"Chimaera+Bugs":[330005],"Dooku+Sep":[-1],"Chimaera":[118395],"Executrix":[255012],"Nute":[104776],"Poggle Geos":[86713],"Geos-Special":[86713],"NS-NoAssaj":[-1],"DR":[-1],"Geos":[86713],"BH":[131843],"SEE":[-1],"Grievous":[116150]}},{"name":"Velusiia","id":"541224862","values":{"FO":[73600],"Troopers":[66370],"zEP":[127757],"Traya":[96394],"SLKR":[-1],"NS":[70664],"Special":[29356],"Dooku+Asajj":[42316],"Chimaera+Bugs":[297666],"Dooku+Sep":[-1],"Chimaera":[107896],"Executrix":[236814],"Nute":[115825],"Poggle Geos":[94249],"Geos-Special":[94249],"NS-NoAssaj":[-1],"DR":[127302],"Geos":[94249],"BH":[119911],"SEE":[-1],"Grievous":[122080]}},{"name":"Dizzle","id":"566511783","values":{"FO":[-1],"Troopers":[123208],"zEP":[146074],"Traya":[88719],"SLKR":[153400],"NS":[77596],"Special":[29496],"Dooku+Asajj":[38811],"Chimaera+Bugs":[375828],"Dooku+Sep":[-1],"Chimaera":[139762],"Executrix":[280122],"Nute":[116373],"Poggle Geos":[105803],"Geos-Special":[105803],"NS-NoAssaj":[71015],"DR":[130187],"Geos":[105803],"BH":[148774],"SEE":[-1],"Grievous":[128817]}},{"name":"Brooks","id":"596812136","values":{"FO":[-1],"Troopers":[102477],"zEP":[139017],"Traya":[53544],"SLKR":[152522],"NS":[-1],"Special":[28890],"Dooku+Asajj":[28063],"Chimaera+Bugs":[319960],"Dooku+Sep":[-1],"Chimaera":[104888],"Executrix":[250128],"Nute":[107364],"Poggle Geos":[90654],"Geos-Special":[90654],"NS-NoAssaj":[-1],"DR":[-1],"Geos":[90654],"BH":[136609],"SEE":[-1],"Grievous":[121609]}},{"name":"AquaRex","id":"613226156","values":{"FO":[43313],"Troopers":[103981],"zEP":[124933],"Traya":[-1],"SLKR":[-1],"NS":[69194],"Special":[16893],"Dooku+Asajj":[51339],"Chimaera+Bugs":[277727],"Dooku+Sep":[-1],"Chimaera":[103117],"Executrix":[244708],"Nute":[115613],"Poggle Geos":[89679],"DR":[-1],"Geos-Special":[89679],"NS-NoAssaj":[-1],"Geos":[89679],"SEE":[-1],"BH":[98358],"Grievous":[113641]}},{"name":"Auzbeast","id":"637396872","values":{"FO":[85304],"Troopers":[130136],"zEP":[-1],"Traya":[109769],"SLKR":[-1],"NS":[94095],"Special":[-1],"Dooku+Asajj":[55025],"Chimaera+Bugs":[371026],"Dooku+Sep":[-1],"Chimaera":[142471],"Executrix":[282862],"Nute":[115967],"Poggle Geos":[105160],"Geos-Special":[105160],"NS-NoAssaj":[-1],"DR":[135664],"Geos":[105160],"BH":[142811],"SEE":[165492],"Grievous":[127663]}},{"name":"MINI Ruibarian","id":"642573143","values":{"FO":[58133],"Troopers":[111804],"zEP":[142542],"Traya":[76884],"SLKR":[-1],"NS":[71724],"Special":[28750],"Dooku+Asajj":[55238],"Chimaera+Bugs":[352689],"Dooku+Sep":[-1],"Chimaera":[133802],"Executrix":[284774],"Nute":[118269],"Poggle Geos":[94758],"Geos-Special":[94758],"NS-NoAssaj":[-1],"DR":[123622],"Geos":[94758],"BH":[146999],"SEE":[-1],"Grievous":[120260]}},{"name":"snake","id":"647855275","values":{"FO":[-1],"Troopers":[76877],"zEP":[140334],"Traya":[114746],"SLKR":[151589],"NS":[112017],"Special":[19381],"Dooku+Asajj":[44567],"Chimaera+Bugs":[382878],"Dooku+Sep":[-1],"Chimaera":[144245],"Executrix":[275968],"Nute":[102684],"Poggle Geos":[106236],"DR":[144003],"Geos-Special":[106236],"NS-NoAssaj":[-1],"Geos":[106236],"SEE":[-1],"BH":[140759],"Grievous":[115283]}},{"name":"Peregine","id":"649766578","values":{"FO":[-1],"Troopers":[115333],"zEP":[144031],"Traya":[90781],"SLKR":[153154],"NS":[86600],"Special":[29295],"Dooku+Asajj":[42271],"Chimaera+Bugs":[350666],"Dooku+Sep":[-1],"Chimaera":[124845],"Executrix":[262656],"Nute":[111313],"Poggle Geos":[98433],"Geos-Special":[98433],"NS-NoAssaj":[-1],"DR":[134042],"Geos":[98433],"BH":[149169],"SEE":[-1],"Grievous":[124329]}},{"name":"Aceblade","id":"671271358","values":{"FO":[87887],"Troopers":[105871],"zEP":[136899],"Traya":[83570],"SLKR":[-1],"NS":[94446],"Special":[18448],"Dooku+Asajj":[42661],"Chimaera+Bugs":[359693],"Dooku+Sep":[-1],"Chimaera":[138393],"Executrix":[258098],"Nute":[102502],"Poggle Geos":[91090],"DR":[111398],"Geos-Special":[91090],"NS-NoAssaj":[-1],"Geos":[91090],"SEE":[-1],"BH":[135875],"Grievous":[115069]}},{"name":"ManiacalVampire","id":"678136272","values":{"FO":[-1],"Troopers":[100174],"zEP":[126542],"Traya":[98789],"SLKR":[-1],"NS":[-1],"Special":[21576],"Dooku+Asajj":[40041],"Chimaera+Bugs":[315391],"Dooku+Sep":[-1],"Chimaera":[104896],"Executrix":[245863],"Nute":[109291],"Poggle Geos":[102047],"Geos-Special":[102047],"NS-NoAssaj":[-1],"DR":[-1],"Geos":[102047],"BH":[127668],"SEE":[-1],"Grievous":[122354]}},{"name":"Defiant","id":"771977741","values":{"FO":[-1],"Troopers":[109927],"zEP":[-1],"Traya":[97138],"SLKR":[151328],"NS":[96788],"Special":[17272],"Dooku+Asajj":[52951],"Chimaera+Bugs":[358653],"Dooku+Sep":[-1],"Chimaera":[142538],"Executrix":[271369],"Nute":[114499],"Poggle Geos":[96941],"Geos-Special":[96941],"NS-NoAssaj":[-1],"DR":[117989],"Geos":[96941],"BH":[139518],"SEE":[165044],"Grievous":[126124]}},{"name":"Uzichow","id":"787311459","values":{"FO":[91023],"Troopers":[120368],"zEP":[152481],"Traya":[76535],"SLKR":[-1],"NS":[107259],"Special":[29356],"Dooku+Asajj":[56257],"Chimaera+Bugs":[365417],"Dooku+Sep":[-1],"Chimaera":[140635],"Executrix":[271058],"Nute":[111312],"Poggle Geos":[99828],"DR":[139016],"Geos-Special":[99828],"NS-NoAssaj":[-1],"Geos":[99828],"SEE":[-1],"BH":[147059],"Grievous":[124130]}},{"name":"Monkeyisbest","id":"793493441","values":{"FO":[64292],"Troopers":[120480],"zEP":[-1],"Traya":[79835],"SLKR":[-1],"NS":[88639],"Special":[-1],"Dooku+Asajj":[48313],"Chimaera+Bugs":[382415],"Dooku+Sep":[-1],"Chimaera":[147996],"Executrix":[299955],"Nute":[112857],"Poggle Geos":[105994],"Geos-Special":[105994],"NS-NoAssaj":[-1],"DR":[112528],"Geos":[105994],"BH":[139621],"SEE":[170689],"Grievous":[125385]}},{"name":"Winzorg","id":"793632989","values":{"FO":[-1],"Troopers":[86210],"zEP":[111273],"Traya":[-1],"SLKR":[154989],"NS":[63527],"Special":[12723],"Dooku+Asajj":[23896],"Chimaera+Bugs":[345733],"Dooku+Sep":[39199],"Chimaera":[116956],"Executrix":[271273],"Nute":[19638],"Poggle Geos":[101694],"DR":[144716],"Geos-Special":[101694],"NS-NoAssaj":[66597],"Geos":[101694],"SEE":[-1],"BH":[121712],"Grievous":[-1]}},{"name":"Granite Fox","id":"812363892","values":{"FO":[-1],"Troopers":[126017],"zEP":[140859],"Traya":[-1],"SLKR":[154204],"NS":[83699],"Special":[28846],"Dooku+Asajj":[40561],"Chimaera+Bugs":[327937],"Dooku+Sep":[-1],"Chimaera":[106907],"Executrix":[257531],"Nute":[120457],"Poggle Geos":[93312],"Geos-Special":[93312],"NS-NoAssaj":[-1],"DR":[141098],"Geos":[93312],"BH":[142026],"SEE":[-1],"Grievous":[132239]}},{"name":"WizenSlinky","id":"827524916","values":{"FO":[59932],"Troopers":[121590],"zEP":[-1],"Traya":[103671],"SLKR":[-1],"NS":[74699],"Special":[29007],"Chimaera+Bugs":[352380],"Dooku+Asajj":[-1],"Dooku+Sep":[-1],"Chimaera":[136123],"Executrix":[285423],"Nute":[131502],"NS-NoAssaj":[71968],"DR":[121994],"Poggle Geos":[92868],"Geos-Special":[92868],"Geos":[92868],"BH":[146144],"SEE":[178373],"Grievous":[136739]}},{"name":"GeorgeyBoy","id":"838172774","values":{"FO":[-1],"Troopers":[127330],"zEP":[137478],"Traya":[102503],"SLKR":[152612],"NS":[74732],"Special":[-1],"Dooku+Asajj":[28639],"Chimaera+Bugs":[341252],"Dooku+Sep":[-1],"Chimaera":[121141],"Executrix":[261538],"Nute":[94197],"NS-NoAssaj":[-1],"DR":[141668],"Poggle Geos":[92663],"Geos-Special":[92663],"Geos":[92663],"BH":[141674],"SEE":[-1],"Grievous":[120691]}},{"name":"Cidestep","id":"839898512","values":{"FO":[109845],"Troopers":[114537],"zEP":[152283],"Traya":[105914],"SLKR":[-1],"NS":[107489],"Special":[-1],"Chimaera+Bugs":[354414],"Dooku+Asajj":[52575],"Dooku+Sep":[-1],"Chimaera":[144267],"Executrix":[264150],"Nute":[116011],"NS-NoAssaj":[-1],"DR":[110784],"Poggle Geos":[86206],"Geos-Special":[86206],"Geos":[86206],"BH":[146052],"SEE":[-1],"Grievous":[128961]}},{"name":"Bespin Skywalking","id":"846525532","values":{"FO":[69035],"Troopers":[82818],"zEP":[132819],"Traya":[-1],"SLKR":[-1],"NS":[85815],"Special":[-1],"Dooku+Asajj":[39908],"Chimaera+Bugs":[344320],"Dooku+Sep":[-1],"Chimaera":[125232],"Executrix":[263669],"Nute":[106430],"NS-NoAssaj":[86048],"DR":[-1],"Poggle Geos":[95028],"Geos-Special":[95028],"Geos":[95028],"BH":[141051],"SEE":[-1],"Grievous":[121064]}},{"name":"Phobos","id":"848671248","values":{"FO":[136080],"Troopers":[119500],"zEP":[-1],"Traya":[108987],"SLKR":[-1],"NS":[104518],"Special":[25707],"Chimaera+Bugs":[381058],"Dooku+Asajj":[-1],"Dooku+Sep":[-1],"Chimaera":[148586],"Executrix":[292736],"Nute":[120448],"NS-NoAssaj":[-1],"DR":[136112],"Poggle Geos":[103206],"Geos-Special":[103206],"Geos":[103206],"BH":[137321],"SEE":[166310],"Grievous":[128458]}},{"name":"Awakened","id":"855626143","values":{"FO":[80589],"Troopers":[114999],"zEP":[148475],"Traya":[102954],"SLKR":[-1],"NS":[106923],"Special":[29007],"Chimaera+Bugs":[347790],"Dooku+Asajj":[49769],"Dooku+Sep":[-1],"Chimaera":[120578],"Executrix":[273637],"Nute":[114790],"NS-NoAssaj":[-1],"Poggle Geos":[102773],"Geos-Special":[102773],"DR":[128710],"Geos":[102773],"BH":[146664],"SEE":[-1],"Grievous":[127622]}},{"name":"Agangofbears","id":"866558338","values":{"FO":[65865],"Troopers":[125404],"zEP":[-1],"Traya":[93100],"SLKR":[-1],"NS":[81071],"Special":[29074],"Chimaera+Bugs":[382602],"Dooku+Asajj":[-1],"Dooku+Sep":[-1],"Chimaera":[147601],"Executrix":[302040],"Nute":[129142],"NS-NoAssaj":[-1],"Poggle Geos":[108520],"Geos-Special":[108520],"DR":[139841],"Geos":[108520],"BH":[154060],"SEE":[178858],"Grievous":[135620]}},{"name":"SirPanda","id":"868699295","values":{"FO":[-1],"Troopers":[76368],"zEP":[132619],"Traya":[-1],"SLKR":[-1],"NS":[75405],"Special":[29077],"Chimaera+Bugs":[377426],"Dooku+Asajj":[41006],"Dooku+Sep":[-1],"Chimaera":[116151],"Executrix":[305202],"Nute":[118414],"Poggle Geos":[117916],"DR":[127865],"Geos-Special":[117916],"NS-NoAssaj":[-1],"Geos":[117916],"BH":[150626],"SEE":[-1],"Grievous":[130288]}},{"name":"Babadook","id":"882439211","values":{"FO":[-1],"Troopers":[131321],"zEP":[-1],"Traya":[82153],"SLKR":[153279],"NS":[100560],"Special":[18001],"Chimaera+Bugs":[373521],"Dooku+Asajj":[51488],"Dooku+Sep":[-1],"Chimaera":[142268],"Executrix":[285584],"Nute":[112761],"Poggle Geos":[106197],"DR":[139944],"Geos-Special":[106197],"NS-NoAssaj":[-1],"Geos":[106197],"BH":[132113],"SEE":[165082],"Grievous":[122269]}},{"name":"C3P0","id":"884979616","values":{"FO":[92521],"Troopers":[88622],"zEP":[128177],"Traya":[-1],"SLKR":[-1],"NS":[84125],"Special":[-1],"Chimaera+Bugs":[343465],"Dooku+Asajj":[43975],"Dooku+Sep":[-1],"Chimaera":[119991],"Executrix":[257957],"Nute":[111816],"Poggle Geos":[98359],"DR":[101707],"Geos-Special":[98359],"NS-NoAssaj":[-1],"Geos":[98359],"BH":[138780],"SEE":[-1],"Grievous":[123729]}},{"name":"ŤUSK","id":"886366465","values":{"FO":[62904],"Troopers":[115151],"zEP":[-1],"Traya":[81124],"SLKR":[-1],"NS":[71227],"Special":[-1],"Chimaera+Bugs":[349271],"Dooku+Asajj":[47976],"Dooku+Sep":[-1],"Chimaera":[134487],"Executrix":[267816],"Nute":[107782],"Poggle Geos":[91743],"DR":[105523],"Geos-Special":[91743],"NS-NoAssaj":[-1],"Geos":[91743],"BH":[140398],"SEE":[162352],"Grievous":[123607]}},{"name":"Laserbeak","id":"912151483","values":{"FO":[102841],"Troopers":[124328],"zEP":[-1],"Traya":[112330],"SLKR":[-1],"NS":[114569],"Special":[28914],"Chimaera+Bugs":[386951],"Dooku+Asajj":[51398],"Dooku+Sep":[-1],"Chimaera":[148505],"Executrix":[304177],"Nute":[118772],"NS-NoAssaj":[-1],"Poggle Geos":[105159],"Geos-Special":[105159],"DR":[128387],"Geos":[105159],"BH":[149278],"SEE":[171576],"Grievous":[129887]}},{"name":"Lizsen Kendet","id":"946189996","values":{"FO":[-1],"Troopers":[111360],"zEP":[129396],"Traya":[71332],"SLKR":[151005],"NS":[92648],"Special":[-1],"Chimaera+Bugs":[334065],"Dooku+Asajj":[43019],"Dooku+Sep":[-1],"Chimaera":[115285],"Executrix":[263076],"Nute":[111169],"Poggle Geos":[92616],"DR":[137381],"Geos-Special":[92616],"NS-NoAssaj":[-1],"Geos":[92616],"BH":[136871],"SEE":[-1],"Grievous":[124999]}}]}