{"y":"gp","dates":["09\/19\/2022","09\/24\/2022"],"series":[{"name":"Kalaene Starki11er","id":"113428295","values":{"Geonosians":[96074,96074],"Nute-Wat":[-1,-1],"Carth":[86798,86798],"FO":[-1,-1],"Clones":[-1,-1],"Wampa (Counter)":[-1,-1],"SionSolo (Counter)":[18265,18265],"Raddus":[-1,-1],"Bad Batch":[-1,-1],"Jawas":[-1,-1],"Wiggs":[-1,-1],"Thragma (Counter)":[-1,-1],"NS":[-1,-1],"EP (Counter, Rebel)":[-1,-1],"padme":[134693,134693],"SEE":[-1,-1],"Disintegration":[-1,-1],"HansMF":[-1,-1],"JKL":[-1,-1],"Executor":[-1,-1],"BH":[95144,95144],"Ewoks":[80464,80464],"GL Rey":[-1,-1],"Maul":[-1,-1],"NestSolo (Counter)":[20118,20118],"zMaul":[-1,-1],"NestSisters":[-1,-1],"Traya":[-1,-1],"CLS":[102359,102359],"QiraNest":[-1,-1],"Troopers":[-1,-1],"JTR":[91950,91950],"JMK":[-1,-1],"NS_Alt":[89160,89160],"Executrix":[-1,-1],"Revan Offense":[108687,108687],"JMLS":[-1,-1],"Grievous-Wat":[-1,-1],"Malevolence":[-1,-1],"Phasma":[75851,75851],"GAS":[125060,125060],"Mon Mothma":[77249,77249],"BS":[-1,-1],"Grievous":[117332,117332],"Qira":[-1,-1],"ShaakClones":[-1,-1],"Phoenix":[83465,83465],"SL Kylo":[-1,-1],"zEP":[100319,100319],"Negotiator":[424647,424647],"Rogue1":[-1,-1],"Iden Troopers":[-1,-1],"DRMalak":[112233,112233],"DR":[-1,-1],"ThrawnTroopers":[-1,-1],"Nute-OR":[-1,-1],"501st":[-1,-1]}},{"name":"Nalyd Legov","id":"117298211","values":{"Geonosians":[98088,98088],"Nute-Wat":[-1,-1],"Carth":[-1,-1],"FO":[-1,-1],"Clones":[-1,-1],"Wampa (Counter)":[-1,-1],"SionSolo (Counter)":[-1,-1],"Raddus":[-1,-1],"Bad Batch":[-1,-1],"Jawas":[-1,-1],"Wiggs":[-1,-1],"Thragma (Counter)":[70677,70677],"NS":[72282,72282],"EP (Counter, Rebel)":[-1,-1],"padme":[135178,135178],"SEE":[-1,-1],"Disintegration":[-1,-1],"HansMF":[373511,382398],"JKL":[-1,-1],"Executor":[-1,-1],"BH":[100110,100110],"Ewoks":[92266,92266],"GL Rey":[-1,-1],"Maul":[-1,-1],"NestSolo (Counter)":[-1,-1],"zMaul":[-1,-1],"NestSisters":[-1,-1],"Traya":[-1,-1],"CLS":[126585,126585],"QiraNest":[-1,-1],"Troopers":[120949,120949],"JTR":[-1,-1],"JMK":[-1,-1],"NS_Alt":[-1,-1],"Executrix":[-1,-1],"Revan Offense":[108240,109933],"JMLS":[-1,-1],"Grievous-Wat":[-1,-1],"Malevolence":[-1,-1],"Phasma":[47149,47149],"GAS":[144494,144494],"Mon Mothma":[-1,-1],"BS":[-1,-1],"Grievous":[115104,115104],"Qira":[-1,-1],"ShaakClones":[-1,-1],"Phoenix":[64438,64438],"SL Kylo":[-1,-1],"zEP":[98009,98009],"Negotiator":[458539,458539],"Rogue1":[59154,60294],"Iden Troopers":[-1,-1],"DRMalak":[-1,-1],"DR":[-1,-1],"ThrawnTroopers":[-1,-1],"Nute-OR":[-1,-1],"501st":[-1,-1]}},{"name":"Austin","id":"134846683","values":{"Geonosians":[77054,77054],"Nute-Wat":[-1,-1],"Carth":[82633,82611],"FO":[-1,-1],"Clones":[-1,-1],"Wampa (Counter)":[-1,-1],"SionSolo (Counter)":[-1,-1],"Raddus":[-1,-1],"Bad Batch":[-1,-1],"Jawas":[-1,-1],"Wiggs":[-1,-1],"Thragma (Counter)":[-1,-1],"NS":[-1,-1],"EP (Counter, Rebel)":[-1,-1],"padme":[-1,-1],"SEE":[-1,-1],"Disintegration":[-1,-1],"HansMF":[332353,332353],"JKL":[118449,120347],"Executor":[-1,-1],"BH":[112317,112317],"Ewoks":[81744,81744],"GL Rey":[-1,-1],"Maul":[-1,-1],"NestSolo (Counter)":[-1,-1],"zMaul":[-1,-1],"NestSisters":[100617,100617],"Traya":[112558,112534],"CLS":[140960,140960],"QiraNest":[-1,-1],"Troopers":[119799,119799],"JTR":[106263,107384],"JMK":[164311,164311],"NS_Alt":[-1,-1],"Executrix":[378811,378811],"Revan Offense":[-1,-1],"JMLS":[-1,-1],"Grievous-Wat":[135979,135979],"Malevolence":[280773,280773],"Phasma":[124063,124063],"GAS":[141792,141792],"Mon Mothma":[94859,94859],"BS":[-1,-1],"Grievous":[-1,-1],"Qira":[-1,-1],"ShaakClones":[-1,-1],"Phoenix":[69030,69030],"SL Kylo":[144611,144611],"zEP":[-1,-1],"Negotiator":[475284,475284],"Rogue1":[-1,-1],"Iden Troopers":[-1,-1],"DRMalak":[115616,115616],"DR":[-1,-1],"ThrawnTroopers":[-1,-1],"Nute-OR":[-1,-1],"501st":[-1,-1]}},{"name":"Warp the Errant","id":"156635713","values":{"Geonosians":[73856,73856],"Nute-Wat":[-1,-1],"Carth":[101638,101638],"FO":[-1,-1],"Clones":[-1,-1],"Wampa (Counter)":[-1,-1],"SionSolo (Counter)":[-1,-1],"Raddus":[-1,-1],"Bad Batch":[-1,-1],"Jawas":[68444,68444],"Wiggs":[89928,89928],"Thragma (Counter)":[-1,-1],"NS":[61749,61749],"EP (Counter, Rebel)":[-1,-1],"padme":[132275,132275],"SEE":[-1,-1],"Disintegration":[-1,-1],"HansMF":[-1,-1],"JKL":[-1,-1],"Executor":[-1,-1],"BH":[100674,100674],"Ewoks":[88847,88847],"GL Rey":[-1,-1],"Maul":[-1,-1],"NestSolo (Counter)":[-1,-1],"zMaul":[76694,76694],"NestSisters":[-1,-1],"Traya":[-1,-1],"CLS":[108310,108310],"QiraNest":[-1,-1],"Troopers":[77762,77762],"JTR":[-1,-1],"JMK":[-1,-1],"NS_Alt":[-1,-1],"Executrix":[-1,-1],"Revan Offense":[123953,123953],"JMLS":[-1,-1],"Grievous-Wat":[-1,-1],"Malevolence":[-1,-1],"Phasma":[49864,49864],"GAS":[-1,-1],"Mon Mothma":[78221,78221],"BS":[-1,-1],"Grievous":[84177,84177],"Qira":[-1,-1],"ShaakClones":[153028,153028],"Phoenix":[61804,61804],"SL Kylo":[-1,-1],"zEP":[111233,111233],"Negotiator":[469319,469319],"Rogue1":[-1,-1],"Iden Troopers":[-1,-1],"DRMalak":[113890,113890],"DR":[-1,-1],"ThrawnTroopers":[-1,-1],"Nute-OR":[-1,-1],"501st":[-1,-1]}},{"name":"Felidererste","id":"164112683","values":{"Geonosians":[95672,95744],"Nute-Wat":[-1,-1],"Carth":[61214,61336],"FO":[-1,-1],"Clones":[96602,96602],"Wampa (Counter)":[-1,-1],"SionSolo (Counter)":[-1,-1],"Raddus":[475538,475783],"Bad Batch":[-1,-1],"Jawas":[60068,64037],"Wiggs":[-1,-1],"Thragma (Counter)":[-1,-1],"NS":[85129,85400],"EP (Counter, Rebel)":[-1,-1],"padme":[130523,131019],"SEE":[-1,-1],"Disintegration":[-1,-1],"HansMF":[-1,-1],"JKL":[-1,-1],"Executor":[-1,-1],"BH":[115063,115087],"Ewoks":[98569,98569],"GL Rey":[141835,143179],"Maul":[-1,-1],"NestSolo (Counter)":[-1,-1],"zMaul":[-1,-1],"NestSisters":[-1,-1],"Traya":[126167,126233],"CLS":[135047,135182],"QiraNest":[-1,-1],"Troopers":[68750,68750],"JTR":[-1,-1],"JMK":[-1,-1],"NS_Alt":[-1,-1],"Executrix":[-1,-1],"Revan Offense":[146139,146139],"JMLS":[-1,-1],"Grievous-Wat":[-1,-1],"Malevolence":[-1,-1],"Phasma":[105272,105272],"GAS":[-1,-1],"Mon Mothma":[63102,63258],"BS":[-1,-1],"Grievous":[72079,72417],"Qira":[-1,-1],"ShaakClones":[-1,-1],"Phoenix":[66840,67111],"SL Kylo":[-1,-1],"zEP":[114719,114719],"Negotiator":[434972,435478],"Rogue1":[43618,45617],"Iden Troopers":[-1,-1],"DRMalak":[-1,-1],"DR":[-1,-1],"ThrawnTroopers":[-1,-1],"Nute-OR":[-1,-1],"501st":[-1,-1]}},{"name":"Ewrecked","id":"164492362","values":{"Geonosians":[105834,105834],"Nute-Wat":[-1,-1],"Carth":[98358,98358],"FO":[116591,116591],"Clones":[-1,-1],"Wampa (Counter)":[-1,-1],"SionSolo (Counter)":[20152,20152],"Raddus":[-1,-1],"Bad Batch":[-1,-1],"Jawas":[109675,109675],"Wiggs":[-1,-1],"Thragma (Counter)":[88734,92494],"NS":[117323,117323],"EP (Counter, Rebel)":[-1,-1],"padme":[138798,138798],"SEE":[-1,-1],"Disintegration":[-1,-1],"HansMF":[414984,414984],"JKL":[-1,-1],"Executor":[-1,-1],"BH":[128079,128079],"Ewoks":[84780,84780],"GL Rey":[-1,-1],"Maul":[-1,-1],"NestSolo (Counter)":[-1,-1],"zMaul":[100749,100749],"NestSisters":[-1,-1],"Traya":[-1,-1],"CLS":[149827,149827],"QiraNest":[-1,-1],"Troopers":[115194,115194],"JTR":[-1,-1],"JMK":[-1,-1],"NS_Alt":[-1,-1],"Executrix":[392342,392342],"Revan Offense":[-1,-1],"JMLS":[170654,170654],"Grievous-Wat":[-1,-1],"Malevolence":[-1,-1],"Phasma":[-1,-1],"GAS":[-1,-1],"Mon Mothma":[111153,111153],"BS":[-1,-1],"Grievous":[128944,128944],"Qira":[-1,-1],"ShaakClones":[137345,137345],"Phoenix":[103678,103678],"SL Kylo":[-1,-1],"zEP":[122686,122686],"Negotiator":[484671,484671],"Rogue1":[-1,-1],"Iden Troopers":[-1,-1],"DRMalak":[134528,134528],"DR":[-1,-1],"ThrawnTroopers":[-1,-1],"Nute-OR":[-1,-1],"501st":[-1,-1]}},{"name":"MonkeyOfBorealValley","id":"175631523","values":{"Geonosians":[91817,91817],"Nute-Wat":[-1,-1],"Carth":[87594,87594],"FO":[-1,-1],"Clones":[-1,-1],"Wampa (Counter)":[-1,-1],"SionSolo (Counter)":[-1,-1],"Raddus":[-1,-1],"Bad Batch":[92771,92771],"Jawas":[-1,-1],"Wiggs":[-1,-1],"Thragma (Counter)":[-1,-1],"NS":[85522,85522],"EP (Counter, Rebel)":[-1,-1],"padme":[121799,121799],"SEE":[-1,-1],"Disintegration":[-1,-1],"HansMF":[381452,381809],"JKL":[-1,-1],"Executor":[-1,-1],"BH":[93297,93297],"Ewoks":[77737,77737],"GL Rey":[-1,-1],"Maul":[-1,-1],"NestSolo (Counter)":[16207,16207],"zMaul":[-1,-1],"NestSisters":[-1,-1],"Traya":[106453,106453],"CLS":[122118,122118],"QiraNest":[-1,-1],"Troopers":[89605,89605],"JTR":[-1,-1],"JMK":[-1,-1],"NS_Alt":[-1,-1],"Executrix":[-1,-1],"Revan Offense":[112731,113662],"JMLS":[-1,-1],"Grievous-Wat":[-1,-1],"Malevolence":[278310,282668],"Phasma":[-1,-1],"GAS":[137664,137664],"Mon Mothma":[92499,88377],"BS":[-1,-1],"Grievous":[105961,105961],"Qira":[-1,-1],"ShaakClones":[-1,-1],"Phoenix":[70994,71390],"SL Kylo":[-1,-1],"zEP":[-1,-1],"Negotiator":[433911,433911],"Rogue1":[-1,-1],"Iden Troopers":[-1,-1],"DRMalak":[125026,125335],"DR":[-1,-1],"ThrawnTroopers":[-1,-1],"Nute-OR":[-1,-1],"501st":[-1,-1]}},{"name":"Lasod Zur'lov","id":"212765237","values":{"Geonosians":[112406,112406],"Nute-Wat":[-1,-1],"Carth":[-1,-1],"FO":[-1,-1],"Clones":[-1,-1],"Wampa (Counter)":[-1,-1],"SionSolo (Counter)":[-1,-1],"Raddus":[-1,-1],"Bad Batch":[130311,130311],"Jawas":[66397,66397],"Wiggs":[-1,-1],"Thragma (Counter)":[-1,-1],"NS":[105371,105371],"EP (Counter, Rebel)":[-1,-1],"padme":[-1,-1],"SEE":[160829,160829],"Disintegration":[117097,117097],"HansMF":[476289,479832],"JKL":[141849,141849],"Executor":[570586,570685],"BH":[-1,-1],"Ewoks":[81868,81868],"GL Rey":[164438,164438],"Maul":[133322,133322],"NestSolo (Counter)":[23613,23613],"zMaul":[-1,-1],"NestSisters":[-1,-1],"Traya":[145076,145076],"CLS":[151027,151027],"QiraNest":[-1,-1],"Troopers":[127345,127394],"JTR":[-1,-1],"JMK":[180494,180494],"NS_Alt":[-1,-1],"Executrix":[-1,-1],"Revan Offense":[-1,-1],"JMLS":[-1,-1],"Grievous-Wat":[-1,-1],"Malevolence":[336258,336258],"Phasma":[123851,123851],"GAS":[-1,-1],"Mon Mothma":[105444,105444],"BS":[-1,-1],"Grievous":[127150,127150],"Qira":[98458,98458],"ShaakClones":[152091,152091],"Phoenix":[74964,75780],"SL Kylo":[155072,155072],"zEP":[-1,-1],"Negotiator":[528086,528186],"Rogue1":[100679,102846],"Iden Troopers":[84256,84256],"DRMalak":[-1,-1],"DR":[-1,-1],"ThrawnTroopers":[-1,-1],"Nute-OR":[-1,-1],"501st":[-1,-1]}},{"name":"HypodriveBundle0dot00","id":"224628997","values":{"Geonosians":[92341,92341],"Nute-Wat":[-1,-1],"Carth":[88256,88256],"FO":[-1,-1],"Clones":[-1,-1],"Wampa (Counter)":[-1,-1],"SionSolo (Counter)":[13062,14640],"Raddus":[-1,-1],"Bad Batch":[-1,-1],"Jawas":[-1,-1],"Wiggs":[-1,-1],"Thragma (Counter)":[-1,-1],"NS":[58880,58880],"EP (Counter, Rebel)":[-1,-1],"padme":[-1,-1],"SEE":[-1,-1],"Disintegration":[105596,105596],"HansMF":[316566,317099],"JKL":[-1,117500],"Executor":[558419,558419],"BH":[125895,125895],"Ewoks":[-1,-1],"GL Rey":[-1,-1],"Maul":[-1,-1],"NestSolo (Counter)":[-1,-1],"zMaul":[-1,-1],"NestSisters":[-1,-1],"Traya":[-1,-1],"CLS":[128061,128061],"QiraNest":[-1,-1],"Troopers":[63303,64329],"JTR":[-1,-1],"JMK":[168325,160181],"NS_Alt":[-1,-1],"Executrix":[-1,-1],"Revan Offense":[-1,126344],"JMLS":[-1,-1],"Grievous-Wat":[-1,-1],"Malevolence":[302085,302085],"Phasma":[57115,57115],"GAS":[143478,143478],"Mon Mothma":[70509,70509],"BS":[-1,-1],"Grievous":[118678,118678],"Qira":[-1,-1],"ShaakClones":[-1,-1],"Phoenix":[64708,64708],"SL Kylo":[-1,-1],"zEP":[117212,117212],"Negotiator":[506284,506284],"Rogue1":[-1,-1],"Iden Troopers":[-1,-1],"DRMalak":[-1,-1],"DR":[-1,-1],"ThrawnTroopers":[88183,90491],"Nute-OR":[-1,-1],"501st":[-1,-1]}},{"name":"Hudd","id":"242611463","values":{"Geonosians":[113725,113725],"Nute-Wat":[-1,-1],"Carth":[99870,100476],"FO":[98568,98568],"Clones":[-1,-1],"Wampa (Counter)":[-1,-1],"SionSolo (Counter)":[-1,-1],"Raddus":[-1,-1],"Bad Batch":[70160,70160],"Jawas":[68436,68436],"Wiggs":[86656,86656],"Thragma (Counter)":[-1,-1],"NS":[103393,103393],"EP (Counter, Rebel)":[125768,125768],"padme":[-1,-1],"SEE":[163178,163178],"Disintegration":[-1,-1],"HansMF":[437296,437296],"JKL":[-1,-1],"Executor":[-1,-1],"BH":[137661,139926],"Ewoks":[87958,87958],"GL Rey":[-1,-1],"Maul":[-1,-1],"NestSolo (Counter)":[-1,-1],"zMaul":[128175,128175],"NestSisters":[-1,-1],"Traya":[119305,119305],"CLS":[134693,134693],"QiraNest":[-1,-1],"Troopers":[119502,119502],"JTR":[-1,-1],"JMK":[171848,171848],"NS_Alt":[-1,-1],"Executrix":[472401,472401],"Revan Offense":[142892,142892],"JMLS":[-1,-1],"Grievous-Wat":[-1,-1],"Malevolence":[336035,336035],"Phasma":[-1,-1],"GAS":[-1,-1],"Mon Mothma":[105564,106772],"BS":[-1,-1],"Grievous":[126480,126480],"Qira":[-1,-1],"ShaakClones":[150387,150387],"Phoenix":[81908,81908],"SL Kylo":[-1,-1],"zEP":[-1,-1],"Negotiator":[523895,523895],"Rogue1":[85631,85631],"Iden Troopers":[-1,-1],"DRMalak":[-1,-1],"DR":[-1,-1],"ThrawnTroopers":[-1,-1],"Nute-OR":[-1,-1],"501st":[-1,-1]}},{"name":"Jakuu Bombassa","id":"276331283","values":{"Geonosians":[98419,98419],"Nute-Wat":[111543,111543],"Carth":[93626,93626],"FO":[-1,-1],"Clones":[-1,-1],"Wampa (Counter)":[103528,103528],"SionSolo (Counter)":[-1,-1],"Raddus":[-1,-1],"Bad Batch":[-1,-1],"Jawas":[55785,55785],"Wiggs":[-1,-1],"Thragma (Counter)":[-1,-1],"NS":[114866,114866],"EP (Counter, Rebel)":[-1,-1],"padme":[145143,145143],"SEE":[172993,172993],"Disintegration":[-1,-1],"HansMF":[371355,371355],"JKL":[-1,-1],"Executor":[-1,-1],"BH":[132546,132546],"Ewoks":[90588,90588],"GL Rey":[-1,-1],"Maul":[-1,-1],"NestSolo (Counter)":[-1,-1],"zMaul":[-1,-1],"NestSisters":[-1,-1],"Traya":[120067,120067],"CLS":[116671,116671],"QiraNest":[-1,-1],"Troopers":[105160,105160],"JTR":[115717,115717],"JMK":[-1,-1],"NS_Alt":[-1,-1],"Executrix":[429393,429393],"Revan Offense":[116299,116299],"JMLS":[-1,-1],"Grievous-Wat":[-1,-1],"Malevolence":[287379,287379],"Phasma":[120892,120892],"GAS":[-1,-1],"Mon Mothma":[84071,84071],"BS":[-1,-1],"Grievous":[118224,118224],"Qira":[-1,-1],"ShaakClones":[-1,-1],"Phoenix":[81576,81576],"SL Kylo":[157688,157688],"zEP":[-1,-1],"Negotiator":[462780,462780],"Rogue1":[-1,-1],"Iden Troopers":[59734,59734],"DRMalak":[-1,-1],"DR":[-1,-1],"ThrawnTroopers":[-1,-1],"Nute-OR":[-1,-1],"501st":[-1,-1]}},{"name":"TheIrishBuddaha","id":"285796775","values":{"Geonosians":[95024,95024],"Nute-Wat":[-1,-1],"Carth":[100360,100360],"FO":[-1,-1],"Clones":[-1,-1],"Wampa (Counter)":[-1,-1],"SionSolo (Counter)":[10428,10428],"Raddus":[-1,-1],"Bad Batch":[-1,-1],"Jawas":[-1,-1],"Wiggs":[95331,95331],"Thragma (Counter)":[-1,-1],"NS":[71943,71943],"EP (Counter, Rebel)":[-1,-1],"padme":[142847,142847],"SEE":[-1,-1],"Disintegration":[-1,-1],"HansMF":[382319,382319],"JKL":[-1,-1],"Executor":[-1,-1],"BH":[120126,120126],"Ewoks":[98142,98142],"GL Rey":[-1,-1],"Maul":[-1,-1],"NestSolo (Counter)":[19578,19578],"zMaul":[91355,91775],"NestSisters":[-1,-1],"Traya":[-1,-1],"CLS":[125649,125649],"QiraNest":[-1,-1],"Troopers":[80476,80476],"JTR":[-1,-1],"JMK":[-1,-1],"NS_Alt":[-1,-1],"Executrix":[306762,306762],"Revan Offense":[142029,142029],"JMLS":[-1,-1],"Grievous-Wat":[-1,-1],"Malevolence":[-1,-1],"Phasma":[83260,83260],"GAS":[-1,-1],"Mon Mothma":[-1,-1],"BS":[-1,-1],"Grievous":[131704,131704],"Qira":[-1,-1],"ShaakClones":[100815,100815],"Phoenix":[80922,80922],"SL Kylo":[-1,-1],"zEP":[109679,109679],"Negotiator":[443947,443947],"Rogue1":[-1,-1],"Iden Troopers":[-1,-1],"DRMalak":[-1,-1],"DR":[113647,113647],"ThrawnTroopers":[-1,-1],"Nute-OR":[-1,-1],"501st":[-1,-1]}},{"name":"Jackjv21","id":"311221786","values":{"Geonosians":[104239,104239],"Nute-Wat":[-1,-1],"Carth":[108072,108072],"FO":[-1,-1],"Clones":[-1,-1],"Wampa (Counter)":[-1,-1],"SionSolo (Counter)":[-1,-1],"Raddus":[-1,-1],"Bad Batch":[129410,131741],"Jawas":[64966,64966],"Wiggs":[66796,66796],"Thragma (Counter)":[-1,-1],"NS":[-1,-1],"EP (Counter, Rebel)":[-1,-1],"padme":[-1,-1],"SEE":[169668,169684],"Disintegration":[131914,131914],"HansMF":[369939,369939],"JKL":[-1,-1],"Executor":[-1,-1],"BH":[122329,122329],"Ewoks":[86886,86886],"GL Rey":[158879,158879],"Maul":[-1,-1],"NestSolo (Counter)":[-1,-1],"zMaul":[124600,124600],"NestSisters":[108763,108763],"Traya":[138884,138884],"CLS":[133150,133150],"QiraNest":[-1,-1],"Troopers":[125168,125168],"JTR":[-1,-1],"JMK":[-1,-1],"NS_Alt":[-1,-1],"Executrix":[-1,-1],"Revan Offense":[145261,145261],"JMLS":[-1,-1],"Grievous-Wat":[-1,-1],"Malevolence":[-1,-1],"Phasma":[123204,123204],"GAS":[136638,136638],"Mon Mothma":[-1,-1],"BS":[-1,-1],"Grievous":[119086,119086],"Qira":[-1,-1],"ShaakClones":[-1,-1],"Phoenix":[76481,76481],"SL Kylo":[161285,161285],"zEP":[-1,-1],"Negotiator":[472951,472951],"Rogue1":[58466,58466],"Iden Troopers":[-1,-1],"DRMalak":[-1,-1],"DR":[-1,-1],"ThrawnTroopers":[-1,-1],"Nute-OR":[-1,-1],"501st":[-1,-1]}},{"name":"Sleazebot","id":"357179512","values":{"Geonosians":[124468,124468],"Nute-Wat":[-1,-1],"Carth":[105920,105920],"FO":[87559,87559],"Clones":[-1,-1],"Wampa (Counter)":[-1,-1],"SionSolo (Counter)":[-1,-1],"Raddus":[-1,-1],"Bad Batch":[-1,-1],"Jawas":[36409,36409],"Wiggs":[-1,-1],"Thragma (Counter)":[-1,-1],"NS":[115448,115448],"EP (Counter, Rebel)":[-1,-1],"padme":[142823,144407],"SEE":[-1,-1],"Disintegration":[-1,-1],"HansMF":[395181,396806],"JKL":[-1,-1],"Executor":[-1,-1],"BH":[112260,112260],"Ewoks":[95056,95056],"GL Rey":[-1,-1],"Maul":[-1,-1],"NestSolo (Counter)":[17269,17269],"zMaul":[-1,-1],"NestSisters":[-1,-1],"Traya":[91546,91546],"CLS":[138479,138479],"QiraNest":[-1,-1],"Troopers":[91401,91401],"JTR":[-1,-1],"JMK":[-1,-1],"NS_Alt":[-1,-1],"Executrix":[324424,324424],"Revan Offense":[133479,133479],"JMLS":[-1,-1],"Grievous-Wat":[-1,-1],"Malevolence":[341031,341031],"Phasma":[-1,-1],"GAS":[-1,-1],"Mon Mothma":[97194,97194],"BS":[-1,-1],"Grievous":[125966,125966],"Qira":[-1,-1],"ShaakClones":[135117,135117],"Phoenix":[97463,99267],"SL Kylo":[-1,-1],"zEP":[104026,104026],"Negotiator":[464550,468114],"Rogue1":[41151,41151],"Iden Troopers":[-1,-1],"DRMalak":[120302,120302],"DR":[-1,-1],"ThrawnTroopers":[-1,-1],"Nute-OR":[-1,-1],"501st":[-1,-1]}},{"name":"McTavva","id":"381694284","values":{"Geonosians":[106796,106796],"Nute-Wat":[-1,-1],"Carth":[95038,95038],"FO":[-1,-1],"Clones":[-1,-1],"Wampa (Counter)":[-1,-1],"SionSolo (Counter)":[10882,10882],"Raddus":[-1,-1],"Bad Batch":[66992,66992],"Jawas":[-1,-1],"Wiggs":[-1,-1],"Thragma (Counter)":[92642,92642],"NS":[-1,-1],"EP (Counter, Rebel)":[-1,-1],"padme":[149293,149293],"SEE":[-1,-1],"Disintegration":[-1,-1],"HansMF":[-1,-1],"JKL":[-1,-1],"Executor":[-1,-1],"BH":[117637,117637],"Ewoks":[87177,87177],"GL Rey":[-1,-1],"Maul":[-1,-1],"NestSolo (Counter)":[23791,23791],"zMaul":[-1,-1],"NestSisters":[-1,-1],"Traya":[-1,-1],"CLS":[121948,121948],"QiraNest":[-1,-1],"Troopers":[121951,121951],"JTR":[-1,-1],"JMK":[-1,-1],"NS_Alt":[-1,-1],"Executrix":[-1,-1],"Revan Offense":[122320,122320],"JMLS":[-1,-1],"Grievous-Wat":[-1,-1],"Malevolence":[-1,-1],"Phasma":[83904,83904],"GAS":[147530,147530],"Mon Mothma":[102288,102288],"BS":[-1,-1],"Grievous":[135822,135822],"Qira":[-1,-1],"ShaakClones":[-1,-1],"Phoenix":[72588,72588],"SL Kylo":[-1,-1],"zEP":[134775,134775],"Negotiator":[496348,496348],"Rogue1":[-1,-1],"Iden Troopers":[-1,-1],"DRMalak":[-1,-1],"DR":[111258,111258],"ThrawnTroopers":[-1,-1],"Nute-OR":[-1,-1],"501st":[-1,-1]}},{"name":"KELLVES","id":"449438138","values":{"Geonosians":[105712,105712],"Nute-Wat":[-1,-1],"Carth":[91162,91162],"FO":[-1,-1],"Clones":[-1,-1],"Wampa (Counter)":[-1,-1],"SionSolo (Counter)":[-1,-1],"Raddus":[-1,-1],"Bad Batch":[68152,68152],"Jawas":[55169,55169],"Wiggs":[-1,-1],"Thragma (Counter)":[-1,-1],"NS":[87849,87849],"EP (Counter, Rebel)":[-1,-1],"padme":[114923,114923],"SEE":[-1,-1],"Disintegration":[-1,-1],"HansMF":[-1,-1],"JKL":[-1,-1],"Executor":[-1,-1],"BH":[104300,104300],"Ewoks":[103366,103366],"GL Rey":[-1,-1],"Maul":[-1,-1],"NestSolo (Counter)":[19848,19848],"zMaul":[-1,-1],"NestSisters":[-1,-1],"Traya":[108162,109725],"CLS":[112198,112198],"QiraNest":[-1,-1],"Troopers":[73856,73856],"JTR":[-1,-1],"JMK":[-1,-1],"NS_Alt":[-1,-1],"Executrix":[-1,-1],"Revan Offense":[121403,121403],"JMLS":[-1,-1],"Grievous-Wat":[-1,-1],"Malevolence":[-1,-1],"Phasma":[123530,123530],"GAS":[-1,-1],"Mon Mothma":[81383,81383],"BS":[-1,-1],"Grievous":[113560,113560],"Qira":[-1,-1],"ShaakClones":[112087,112087],"Phoenix":[79831,79831],"SL Kylo":[-1,-1],"zEP":[-1,-1],"Negotiator":[377801,377801],"Rogue1":[-1,-1],"Iden Troopers":[-1,-1],"DRMalak":[-1,-1],"DR":[106247,106247],"ThrawnTroopers":[-1,-1],"Nute-OR":[-1,-1],"501st":[-1,-1]}},{"name":"Corran Horn","id":"449517421","values":{"Geonosians":[96440,96440],"Nute-Wat":[-1,-1],"Carth":[95159,95159],"FO":[-1,-1],"Clones":[-1,-1],"Wampa (Counter)":[-1,-1],"SionSolo (Counter)":[-1,-1],"Raddus":[-1,-1],"Bad Batch":[70443,70443],"Jawas":[-1,-1],"Wiggs":[70050,70050],"Thragma (Counter)":[-1,-1],"NS":[94791,94791],"EP (Counter, Rebel)":[-1,-1],"padme":[137951,137951],"SEE":[-1,-1],"Disintegration":[-1,-1],"HansMF":[346941,346941],"JKL":[-1,-1],"Executor":[-1,-1],"BH":[113233,113233],"Ewoks":[82723,82723],"GL Rey":[-1,-1],"Maul":[-1,-1],"NestSolo (Counter)":[20058,20058],"zMaul":[-1,-1],"NestSisters":[-1,-1],"Traya":[125911,125911],"CLS":[113840,113840],"QiraNest":[-1,-1],"Troopers":[111589,114304],"JTR":[-1,-1],"JMK":[-1,-1],"NS_Alt":[-1,-1],"Executrix":[-1,-1],"Revan Offense":[124009,124009],"JMLS":[-1,-1],"Grievous-Wat":[-1,-1],"Malevolence":[279664,279664],"Phasma":[122323,122323],"GAS":[-1,-1],"Mon Mothma":[76797,76797],"BS":[-1,-1],"Grievous":[123876,123876],"Qira":[-1,-1],"ShaakClones":[134982,134982],"Phoenix":[65939,65939],"SL Kylo":[156935,156935],"zEP":[-1,-1],"Negotiator":[484142,484142],"Rogue1":[-1,-1],"Iden Troopers":[-1,-1],"DRMalak":[128108,128108],"DR":[-1,-1],"ThrawnTroopers":[-1,-1],"Nute-OR":[-1,-1],"501st":[-1,-1]}},{"name":"Suspekt","id":"452669286","values":{"Geonosians":[118548,118548],"Nute-Wat":[-1,-1],"Carth":[109057,109057],"FO":[109870,109870],"Clones":[-1,-1],"Wampa (Counter)":[-1,-1],"SionSolo (Counter)":[-1,-1],"Raddus":[-1,-1],"Bad Batch":[-1,-1],"Jawas":[56419,56419],"Wiggs":[-1,-1],"Thragma (Counter)":[-1,-1],"NS":[120373,120373],"EP (Counter, Rebel)":[-1,-1],"padme":[133626,133626],"SEE":[-1,-1],"Disintegration":[-1,-1],"HansMF":[402194,403328],"JKL":[-1,-1],"Executor":[-1,-1],"BH":[137648,137648],"Ewoks":[101788,101788],"GL Rey":[-1,-1],"Maul":[-1,-1],"NestSolo (Counter)":[-1,-1],"zMaul":[99325,100311],"NestSisters":[-1,-1],"Traya":[133416,133416],"CLS":[114522,114522],"QiraNest":[-1,-1],"Troopers":[122904,122928],"JTR":[110999,110999],"JMK":[-1,-1],"NS_Alt":[-1,-1],"Executrix":[-1,-1],"Revan Offense":[128674,128674],"JMLS":[-1,-1],"Grievous-Wat":[-1,-1],"Malevolence":[340633,340633],"Phasma":[-1,-1],"GAS":[-1,-1],"Mon Mothma":[-1,-1],"BS":[-1,-1],"Grievous":[131649,131649],"Qira":[-1,-1],"ShaakClones":[130097,130097],"Phoenix":[87075,88209],"SL Kylo":[-1,-1],"zEP":[-1,-1],"Negotiator":[469019,469019],"Rogue1":[65389,65389],"Iden Troopers":[-1,-1],"DRMalak":[130015,130105],"DR":[-1,-1],"ThrawnTroopers":[-1,-1],"Nute-OR":[-1,-1],"501st":[-1,-1]}},{"name":"Smokeythebear","id":"464164779","values":{"Geonosians":[95209,95209],"Nute-Wat":[-1,-1],"Carth":[99219,99219],"FO":[-1,-1],"Clones":[-1,-1],"Wampa (Counter)":[-1,-1],"SionSolo (Counter)":[20722,20722],"Raddus":[-1,-1],"Bad Batch":[69478,69478],"Jawas":[-1,-1],"Wiggs":[-1,-1],"Thragma (Counter)":[84102,84102],"NS":[-1,-1],"EP (Counter, Rebel)":[-1,-1],"padme":[133777,133777],"SEE":[-1,-1],"Disintegration":[-1,-1],"HansMF":[438348,438348],"JKL":[-1,-1],"Executor":[-1,-1],"BH":[141534,141534],"Ewoks":[93049,93049],"GL Rey":[-1,-1],"Maul":[-1,-1],"NestSolo (Counter)":[-1,-1],"zMaul":[-1,-1],"NestSisters":[106057,106057],"Traya":[-1,-1],"CLS":[145956,145956],"QiraNest":[-1,-1],"Troopers":[104045,104045],"JTR":[-1,-1],"JMK":[-1,-1],"NS_Alt":[-1,-1],"Executrix":[405878,405878],"Revan Offense":[-1,-1],"JMLS":[158401,158401],"Grievous-Wat":[-1,-1],"Malevolence":[301198,301198],"Phasma":[103063,103063],"GAS":[-1,-1],"Mon Mothma":[111637,111637],"BS":[-1,-1],"Grievous":[121563,121563],"Qira":[-1,-1],"ShaakClones":[135705,135705],"Phoenix":[97134,97134],"SL Kylo":[-1,-1],"zEP":[122155,122155],"Negotiator":[476601,476601],"Rogue1":[-1,-1],"Iden Troopers":[-1,-1],"DRMalak":[127576,127576],"DR":[-1,-1],"ThrawnTroopers":[-1,-1],"Nute-OR":[-1,-1],"501st":[-1,-1]}},{"name":"Smackdown48","id":"478151954","values":{"Geonosians":[94321,94321],"Nute-Wat":[-1,-1],"Carth":[84604,84604],"FO":[105068,105068],"Clones":[-1,-1],"Wampa (Counter)":[-1,-1],"SionSolo (Counter)":[12877,12877],"Raddus":[-1,-1],"Bad Batch":[-1,-1],"Jawas":[-1,-1],"Wiggs":[-1,-1],"Thragma (Counter)":[75391,75391],"NS":[-1,-1],"EP (Counter, Rebel)":[-1,-1],"padme":[-1,-1],"SEE":[-1,-1],"Disintegration":[-1,-1],"HansMF":[397608,397608],"JKL":[-1,-1],"Executor":[-1,-1],"BH":[143526,143526],"Ewoks":[82204,82204],"GL Rey":[-1,-1],"Maul":[-1,-1],"NestSolo (Counter)":[-1,-1],"zMaul":[-1,-1],"NestSisters":[-1,-1],"Traya":[-1,-1],"CLS":[149933,149933],"QiraNest":[67600,67600],"Troopers":[130144,130144],"JTR":[-1,-1],"JMK":[167307,167307],"NS_Alt":[93079,93079],"Executrix":[384538,384538],"Revan Offense":[-1,-1],"JMLS":[173655,173655],"Grievous-Wat":[-1,-1],"Malevolence":[-1,-1],"Phasma":[-1,-1],"GAS":[-1,-1],"Mon Mothma":[113303,113303],"BS":[-1,-1],"Grievous":[125282,125282],"Qira":[-1,-1],"ShaakClones":[-1,-1],"Phoenix":[74930,74930],"SL Kylo":[-1,-1],"zEP":[123811,123811],"Negotiator":[507372,507372],"Rogue1":[-1,-1],"Iden Troopers":[-1,-1],"DRMalak":[129747,129747],"DR":[-1,-1],"ThrawnTroopers":[-1,-1],"Nute-OR":[-1,-1],"501st":[144855,144855]}},{"name":"DrunkenChewy","id":"525874223","values":{"Geonosians":[57100,57100],"Nute-Wat":[-1,-1],"Carth":[97725,97725],"FO":[-1,-1],"Clones":[-1,-1],"Wampa (Counter)":[-1,-1],"SionSolo (Counter)":[14334,14334],"Raddus":[-1,-1],"Bad Batch":[-1,-1],"Jawas":[49769,49769],"Wiggs":[80363,80363],"Thragma (Counter)":[73678,73678],"NS":[78968,78968],"EP (Counter, Rebel)":[-1,-1],"padme":[125738,125738],"SEE":[-1,-1],"Disintegration":[-1,-1],"HansMF":[-1,-1],"JKL":[-1,-1],"Executor":[-1,-1],"BH":[102560,102560],"Ewoks":[92919,92919],"GL Rey":[-1,-1],"Maul":[-1,-1],"NestSolo (Counter)":[-1,-1],"zMaul":[92441,92441],"NestSisters":[-1,-1],"Traya":[-1,-1],"CLS":[123135,123135],"QiraNest":[-1,-1],"Troopers":[-1,-1],"JTR":[-1,-1],"JMK":[-1,-1],"NS_Alt":[-1,-1],"Executrix":[-1,-1],"Revan Offense":[113439,113439],"JMLS":[-1,-1],"Grievous-Wat":[-1,-1],"Malevolence":[-1,-1],"Phasma":[123480,123480],"GAS":[-1,-1],"Mon Mothma":[-1,-1],"BS":[-1,-1],"Grievous":[91345,93029],"Qira":[-1,-1],"ShaakClones":[123747,123747],"Phoenix":[73811,73811],"SL Kylo":[-1,-1],"zEP":[119558,119558],"Negotiator":[441155,441277],"Rogue1":[-1,-1],"Iden Troopers":[-1,-1],"DRMalak":[135999,136197],"DR":[-1,-1],"ThrawnTroopers":[-1,-1],"Nute-OR":[-1,-1],"501st":[-1,-1]}},{"name":"Dark Helmutt","id":"526651765","values":{"Geonosians":[118311,118311],"Nute-Wat":[-1,-1],"Carth":[-1,-1],"FO":[113213,113213],"Clones":[-1,-1],"Wampa (Counter)":[-1,-1],"SionSolo (Counter)":[-1,-1],"Raddus":[-1,-1],"Bad Batch":[92410,92410],"Jawas":[72309,72309],"Wiggs":[-1,-1],"Thragma (Counter)":[-1,-1],"NS":[105744,105744],"EP (Counter, Rebel)":[-1,-1],"padme":[145572,145572],"SEE":[-1,-1],"Disintegration":[-1,-1],"HansMF":[451993,451993],"JKL":[-1,-1],"Executor":[-1,-1],"BH":[113473,113473],"Ewoks":[85041,85041],"GL Rey":[-1,-1],"Maul":[-1,-1],"NestSolo (Counter)":[-1,-1],"zMaul":[98619,98619],"NestSisters":[-1,-1],"Traya":[125416,125416],"CLS":[149789,149789],"QiraNest":[-1,-1],"Troopers":[91893,91893],"JTR":[-1,-1],"JMK":[-1,-1],"NS_Alt":[-1,-1],"Executrix":[422565,422565],"Revan Offense":[-1,-1],"JMLS":[165513,165513],"Grievous-Wat":[-1,-1],"Malevolence":[329594,329594],"Phasma":[-1,-1],"GAS":[-1,-1],"Mon Mothma":[107003,107003],"BS":[-1,-1],"Grievous":[127315,127315],"Qira":[90061,90061],"ShaakClones":[134184,134184],"Phoenix":[92219,92219],"SL Kylo":[-1,-1],"zEP":[-1,-1],"Negotiator":[481390,481390],"Rogue1":[-1,-1],"Iden Troopers":[-1,-1],"DRMalak":[125958,125958],"DR":[-1,-1],"ThrawnTroopers":[-1,-1],"Nute-OR":[-1,-1],"501st":[-1,-1]}},{"name":"mgottu","id":"544155395","values":{"Geonosians":[102650,103082],"Nute-Wat":[-1,-1],"Carth":[90050,90402],"FO":[87228,87251],"Clones":[-1,-1],"Wampa (Counter)":[-1,-1],"SionSolo (Counter)":[17887,17887],"Raddus":[-1,-1],"Bad Batch":[56616,57022],"Jawas":[-1,-1],"Wiggs":[-1,-1],"Thragma (Counter)":[-1,-1],"NS":[85413,87586],"EP (Counter, Rebel)":[-1,-1],"padme":[139764,139946],"SEE":[-1,-1],"Disintegration":[-1,-1],"HansMF":[333379,334982],"JKL":[-1,-1],"Executor":[-1,-1],"BH":[102629,102856],"Ewoks":[82756,83511],"GL Rey":[-1,-1],"Maul":[-1,-1],"NestSolo (Counter)":[-1,-1],"zMaul":[107273,110868],"NestSisters":[-1,-1],"Traya":[-1,-1],"CLS":[106449,106449],"QiraNest":[-1,-1],"Troopers":[98253,98253],"JTR":[82970,84216],"JMK":[-1,-1],"NS_Alt":[-1,-1],"Executrix":[341671,342962],"Revan Offense":[115513,115513],"JMLS":[-1,-1],"Grievous-Wat":[-1,-1],"Malevolence":[319681,320395],"Phasma":[-1,-1],"GAS":[149345,149345],"Mon Mothma":[60299,60322],"BS":[-1,-1],"Grievous":[124767,124767],"Qira":[-1,-1],"ShaakClones":[-1,-1],"Phoenix":[68789,69288],"SL Kylo":[-1,-1],"zEP":[119053,120436],"Negotiator":[496080,498483],"Rogue1":[-1,-1],"Iden Troopers":[-1,-1],"DRMalak":[127755,127755],"DR":[-1,-1],"ThrawnTroopers":[61212,61212],"Nute-OR":[-1,-1],"501st":[-1,-1]}},{"name":"Vax Grupen","id":"558577232","values":{"Geonosians":[116685,116685],"Nute-Wat":[-1,-1],"Carth":[100230,100230],"FO":[-1,-1],"Clones":[-1,-1],"Wampa (Counter)":[-1,-1],"SionSolo (Counter)":[-1,-1],"Raddus":[-1,-1],"Bad Batch":[72396,72396],"Jawas":[65031,65031],"Wiggs":[-1,-1],"Thragma (Counter)":[-1,-1],"NS":[104846,104846],"EP (Counter, Rebel)":[-1,-1],"padme":[-1,-1],"SEE":[-1,-1],"Disintegration":[-1,-1],"HansMF":[435721,435721],"JKL":[-1,-1],"Executor":[-1,-1],"BH":[137267,137267],"Ewoks":[85933,85933],"GL Rey":[-1,-1],"Maul":[-1,-1],"NestSolo (Counter)":[19801,19801],"zMaul":[-1,-1],"NestSisters":[-1,-1],"Traya":[136703,136703],"CLS":[147753,147819],"QiraNest":[-1,-1],"Troopers":[82711,83899],"JTR":[-1,-1],"JMK":[174480,174612],"NS_Alt":[-1,-1],"Executrix":[430265,430265],"Revan Offense":[155131,155230],"JMLS":[-1,-1],"Grievous-Wat":[-1,-1],"Malevolence":[307356,307356],"Phasma":[109487,109487],"GAS":[-1,-1],"Mon Mothma":[101848,103702],"BS":[-1,-1],"Grievous":[126973,126973],"Qira":[-1,-1],"ShaakClones":[143054,143054],"Phoenix":[92702,92702],"SL Kylo":[-1,-1],"zEP":[-1,-1],"Negotiator":[534963,534963],"Rogue1":[-1,-1],"Iden Troopers":[-1,-1],"DRMalak":[130073,130073],"DR":[-1,-1],"ThrawnTroopers":[-1,-1],"Nute-OR":[-1,-1],"501st":[-1,-1]}},{"name":"Certified Waffle","id":"574564517","values":{"Geonosians":[97610,97610],"Nute-Wat":[78319,78319],"Carth":[77453,77453],"FO":[82370,82370],"Clones":[-1,-1],"Wampa (Counter)":[-1,-1],"SionSolo (Counter)":[-1,-1],"Raddus":[-1,-1],"Bad Batch":[-1,-1],"Jawas":[-1,-1],"Wiggs":[76340,76340],"Thragma (Counter)":[-1,-1],"NS":[-1,-1],"EP (Counter, Rebel)":[-1,-1],"padme":[109624,109624],"SEE":[-1,-1],"Disintegration":[95194,95194],"HansMF":[326148,326148],"JKL":[-1,-1],"Executor":[-1,-1],"BH":[-1,-1],"Ewoks":[98640,98640],"GL Rey":[-1,-1],"Maul":[-1,-1],"NestSolo (Counter)":[-1,-1],"zMaul":[-1,-1],"NestSisters":[-1,-1],"Traya":[-1,-1],"CLS":[-1,-1],"QiraNest":[-1,-1],"Troopers":[85010,85010],"JTR":[99375,99375],"JMK":[-1,-1],"NS_Alt":[104439,104439],"Executrix":[-1,-1],"Revan Offense":[138916,138916],"JMLS":[-1,-1],"Grievous-Wat":[-1,-1],"Malevolence":[228561,228561],"Phasma":[-1,-1],"GAS":[-1,-1],"Mon Mothma":[58112,58112],"BS":[-1,-1],"Grievous":[59913,59913],"Qira":[-1,-1],"ShaakClones":[134607,134607],"Phoenix":[67170,67170],"SL Kylo":[-1,-1],"zEP":[120538,120538],"Negotiator":[372953,372953],"Rogue1":[-1,-1],"Iden Troopers":[-1,-1],"DRMalak":[-1,-1],"DR":[96744,96744],"ThrawnTroopers":[-1,-1],"Nute-OR":[-1,-1],"501st":[-1,-1]}},{"name":"Rex Urhole","id":"584243558","values":{"Geonosians":[108431,108431],"Nute-Wat":[-1,-1],"Carth":[90764,90764],"FO":[-1,-1],"Clones":[-1,-1],"Wampa (Counter)":[-1,-1],"SionSolo (Counter)":[-1,-1],"Raddus":[-1,-1],"Bad Batch":[-1,-1],"Jawas":[85820,85820],"Wiggs":[-1,-1],"Thragma (Counter)":[-1,-1],"NS":[113240,113240],"EP (Counter, Rebel)":[-1,-1],"padme":[133903,133903],"SEE":[-1,-1],"Disintegration":[-1,-1],"HansMF":[403894,403894],"JKL":[-1,-1],"Executor":[-1,-1],"BH":[121918,121918],"Ewoks":[96060,96060],"GL Rey":[-1,-1],"Maul":[-1,-1],"NestSolo (Counter)":[19779,19779],"zMaul":[-1,-1],"NestSisters":[-1,-1],"Traya":[121998,121998],"CLS":[138998,140894],"QiraNest":[-1,-1],"Troopers":[91692,91692],"JTR":[-1,-1],"JMK":[-1,-1],"NS_Alt":[-1,-1],"Executrix":[-1,-1],"Revan Offense":[129937,129937],"JMLS":[-1,-1],"Grievous-Wat":[-1,-1],"Malevolence":[323294,323294],"Phasma":[126058,126058],"GAS":[132963,132963],"Mon Mothma":[88778,89594],"BS":[-1,-1],"Grievous":[124802,124802],"Qira":[-1,-1],"ShaakClones":[-1,-1],"Phoenix":[81678,81678],"SL Kylo":[152925,152925],"zEP":[-1,-1],"Negotiator":[477046,477046],"Rogue1":[-1,-1],"Iden Troopers":[-1,-1],"DRMalak":[135338,135338],"DR":[-1,-1],"ThrawnTroopers":[-1,-1],"Nute-OR":[-1,-1],"501st":[-1,-1]}},{"name":"ScottyStej","id":"612968512","values":{"Geonosians":[108523,108523],"Nute-Wat":[-1,-1],"Carth":[96962,96962],"FO":[-1,-1],"Clones":[-1,-1],"Wampa (Counter)":[-1,-1],"SionSolo (Counter)":[-1,-1],"Raddus":[-1,-1],"Bad Batch":[-1,-1],"Jawas":[66886,66886],"Wiggs":[-1,-1],"Thragma (Counter)":[-1,-1],"NS":[82089,82089],"EP (Counter, Rebel)":[-1,-1],"padme":[130941,130941],"SEE":[-1,-1],"Disintegration":[-1,-1],"HansMF":[-1,-1],"JKL":[-1,-1],"Executor":[-1,-1],"BH":[124416,124416],"Ewoks":[89482,89482],"GL Rey":[-1,-1],"Maul":[-1,-1],"NestSolo (Counter)":[18543,18543],"zMaul":[-1,-1],"NestSisters":[-1,-1],"Traya":[125659,125659],"CLS":[141083,141083],"QiraNest":[-1,-1],"Troopers":[84977,84977],"JTR":[-1,-1],"JMK":[-1,-1],"NS_Alt":[-1,-1],"Executrix":[446873,446873],"Revan Offense":[122461,123487],"JMLS":[-1,-1],"Grievous-Wat":[-1,-1],"Malevolence":[299718,299718],"Phasma":[123000,123000],"GAS":[132167,132167],"Mon Mothma":[-1,-1],"BS":[-1,-1],"Grievous":[116013,116285],"Qira":[-1,-1],"ShaakClones":[-1,-1],"Phoenix":[98507,98507],"SL Kylo":[155316,155316],"zEP":[-1,-1],"Negotiator":[446954,446954],"Rogue1":[-1,-1],"Iden Troopers":[-1,-1],"DRMalak":[138225,138225],"DR":[-1,-1],"ThrawnTroopers":[-1,-1],"Nute-OR":[-1,-1],"501st":[-1,-1]}},{"name":"Shiner","id":"625681477","values":{"Geonosians":[99350,99350],"Nute-Wat":[-1,-1],"Carth":[129156,129156],"FO":[-1,-1],"Clones":[-1,-1],"Wampa (Counter)":[-1,-1],"SionSolo (Counter)":[18240,18240],"Raddus":[-1,-1],"Bad Batch":[-1,-1],"Jawas":[73918,73918],"Wiggs":[-1,-1],"Thragma (Counter)":[-1,-1],"NS":[-1,-1],"EP (Counter, Rebel)":[-1,-1],"padme":[-1,-1],"SEE":[-1,-1],"Disintegration":[-1,-1],"HansMF":[423091,423091],"JKL":[-1,-1],"Executor":[-1,-1],"BH":[124129,124129],"Ewoks":[98194,98194],"GL Rey":[-1,-1],"Maul":[-1,-1],"NestSolo (Counter)":[-1,-1],"zMaul":[105509,105509],"NestSisters":[111748,111748],"Traya":[-1,-1],"CLS":[137079,137079],"QiraNest":[-1,-1],"Troopers":[67388,67388],"JTR":[-1,-1],"JMK":[163588,165283],"NS_Alt":[-1,-1],"Executrix":[-1,-1],"Revan Offense":[-1,-1],"JMLS":[-1,-1],"Grievous-Wat":[-1,-1],"Malevolence":[295506,295506],"Phasma":[127297,127297],"GAS":[121821,121821],"Mon Mothma":[103725,103725],"BS":[-1,-1],"Grievous":[129434,129434],"Qira":[-1,-1],"ShaakClones":[-1,-1],"Phoenix":[91466,91466],"SL Kylo":[155695,155695],"zEP":[120130,120130],"Negotiator":[501157,501157],"Rogue1":[-1,-1],"Iden Troopers":[-1,-1],"DRMalak":[112210,112210],"DR":[-1,-1],"ThrawnTroopers":[-1,-1],"Nute-OR":[-1,-1],"501st":[-1,-1]}},{"name":"Wedgie Antigua","id":"644939851","values":{"Geonosians":[99080,99080],"Nute-Wat":[-1,-1],"Carth":[91361,91361],"FO":[-1,-1],"Clones":[-1,-1],"Wampa (Counter)":[-1,-1],"SionSolo (Counter)":[-1,-1],"Raddus":[-1,-1],"Bad Batch":[-1,-1],"Jawas":[61299,61299],"Wiggs":[-1,-1],"Thragma (Counter)":[-1,-1],"NS":[-1,-1],"EP (Counter, Rebel)":[-1,-1],"padme":[-1,-1],"SEE":[167227,167227],"Disintegration":[122548,122548],"HansMF":[415545,415545],"JKL":[-1,-1],"Executor":[-1,-1],"BH":[129871,129871],"Ewoks":[91907,91907],"GL Rey":[-1,-1],"Maul":[-1,-1],"NestSolo (Counter)":[-1,-1],"zMaul":[-1,-1],"NestSisters":[-1,-1],"Traya":[108247,108247],"CLS":[156507,156507],"QiraNest":[64572,64572],"Troopers":[126302,126302],"JTR":[-1,-1],"JMK":[170610,170610],"NS_Alt":[105395,105395],"Executrix":[-1,-1],"Revan Offense":[-1,-1],"JMLS":[175073,175073],"Grievous-Wat":[-1,-1],"Malevolence":[293570,293570],"Phasma":[128294,128294],"GAS":[-1,-1],"Mon Mothma":[111399,111399],"BS":[-1,-1],"Grievous":[125876,125876],"Qira":[-1,-1],"ShaakClones":[-1,-1],"Phoenix":[88466,88466],"SL Kylo":[-1,-1],"zEP":[-1,-1],"Negotiator":[520231,520231],"Rogue1":[68521,68521],"Iden Troopers":[76014,76014],"DRMalak":[-1,-1],"DR":[-1,-1],"ThrawnTroopers":[-1,-1],"Nute-OR":[-1,-1],"501st":[135106,135106]}},{"name":"Angrywaffles77","id":"687318556","values":{"Geonosians":[104171,104171],"Nute-Wat":[-1,-1],"Carth":[-1,-1],"FO":[-1,-1],"Clones":[-1,-1],"Wampa (Counter)":[112165,112165],"SionSolo (Counter)":[-1,-1],"Raddus":[-1,-1],"Bad Batch":[52216,52216],"Jawas":[65284,65284],"Wiggs":[-1,-1],"Thragma (Counter)":[-1,-1],"NS":[98621,98621],"EP (Counter, Rebel)":[-1,-1],"padme":[142322,142322],"SEE":[156151,156151],"Disintegration":[-1,-1],"HansMF":[361297,361297],"JKL":[-1,-1],"Executor":[-1,-1],"BH":[122921,122921],"Ewoks":[83187,83187],"GL Rey":[-1,-1],"Maul":[-1,-1],"NestSolo (Counter)":[19183,19183],"zMaul":[-1,-1],"NestSisters":[-1,-1],"Traya":[108078,108078],"CLS":[121058,121058],"QiraNest":[-1,-1],"Troopers":[109084,109084],"JTR":[-1,-1],"JMK":[-1,-1],"NS_Alt":[-1,-1],"Executrix":[429596,429596],"Revan Offense":[150676,150676],"JMLS":[-1,-1],"Grievous-Wat":[105334,105334],"Malevolence":[275420,275420],"Phasma":[122850,122850],"GAS":[-1,-1],"Mon Mothma":[77890,77890],"BS":[-1,-1],"Grievous":[-1,-1],"Qira":[-1,-1],"ShaakClones":[-1,-1],"Phoenix":[79004,79004],"SL Kylo":[157319,157319],"zEP":[-1,-1],"Negotiator":[456938,456938],"Rogue1":[68237,68237],"Iden Troopers":[56362,56362],"DRMalak":[-1,-1],"DR":[-1,-1],"ThrawnTroopers":[-1,-1],"Nute-OR":[107874,107874],"501st":[-1,-1]}},{"name":"Boooosh","id":"711686419","values":{"Geonosians":[86091,86091],"Nute-Wat":[-1,-1],"Carth":[-1,-1],"FO":[-1,-1],"Clones":[-1,-1],"Wampa (Counter)":[-1,-1],"SionSolo (Counter)":[-1,-1],"Raddus":[-1,-1],"Bad Batch":[43597,43964],"Jawas":[60393,60393],"Wiggs":[-1,-1],"Thragma (Counter)":[74283,74877],"NS":[76330,76418],"EP (Counter, Rebel)":[-1,-1],"padme":[128652,128697],"SEE":[-1,-1],"Disintegration":[-1,-1],"HansMF":[440627,440688],"JKL":[-1,-1],"Executor":[-1,-1],"BH":[92494,92494],"Ewoks":[82937,82937],"GL Rey":[-1,-1],"Maul":[-1,-1],"NestSolo (Counter)":[-1,12793],"zMaul":[-1,-1],"NestSisters":[-1,-1],"Traya":[71557,65845],"CLS":[133462,133462],"QiraNest":[-1,-1],"Troopers":[-1,-1],"JTR":[119092,119092],"JMK":[-1,-1],"NS_Alt":[-1,-1],"Executrix":[-1,-1],"Revan Offense":[-1,-1],"JMLS":[156123,156172],"Grievous-Wat":[-1,-1],"Malevolence":[-1,-1],"Phasma":[64516,64516],"GAS":[-1,-1],"Mon Mothma":[105058,105058],"BS":[-1,-1],"Grievous":[100374,110394],"Qira":[-1,-1],"ShaakClones":[134645,134645],"Phoenix":[80090,80090],"SL Kylo":[-1,-1],"zEP":[-1,-1],"Negotiator":[447476,447476],"Rogue1":[-1,-1],"Iden Troopers":[-1,-1],"DRMalak":[-1,-1],"DR":[-1,-1],"ThrawnTroopers":[-1,-1],"Nute-OR":[-1,-1],"501st":[-1,-1]}},{"name":"Aaron","id":"714516234","values":{"Geonosians":[93936,93936],"Nute-Wat":[-1,101604],"Carth":[89096,89096],"FO":[-1,-1],"Clones":[-1,-1],"Wampa (Counter)":[-1,-1],"SionSolo (Counter)":[-1,-1],"Raddus":[-1,-1],"Bad Batch":[-1,-1],"Jawas":[51438,51438],"Wiggs":[-1,-1],"Thragma (Counter)":[-1,-1],"NS":[74317,74947],"EP (Counter, Rebel)":[-1,-1],"padme":[127162,127162],"SEE":[-1,-1],"Disintegration":[-1,-1],"HansMF":[400857,400857],"JKL":[-1,-1],"Executor":[-1,-1],"BH":[106251,106251],"Ewoks":[78206,78206],"GL Rey":[-1,-1],"Maul":[-1,-1],"NestSolo (Counter)":[14373,14373],"zMaul":[-1,-1],"NestSisters":[-1,-1],"Traya":[53992,54169],"CLS":[131402,131402],"QiraNest":[-1,-1],"Troopers":[-1,-1],"JTR":[-1,-1],"JMK":[-1,-1],"NS_Alt":[-1,-1],"Executrix":[-1,-1],"Revan Offense":[141243,141243],"JMLS":[-1,-1],"Grievous-Wat":[-1,-1],"Malevolence":[-1,-1],"Phasma":[123339,123339],"GAS":[146950,146950],"Mon Mothma":[90275,90275],"BS":[-1,-1],"Grievous":[-1,106035],"Qira":[-1,-1],"ShaakClones":[-1,-1],"Phoenix":[87630,87630],"SL Kylo":[144908,144908],"zEP":[105158,105158],"Negotiator":[482591,482591],"Rogue1":[48462,48462],"Iden Troopers":[-1,-1],"DRMalak":[117341,117341],"DR":[-1,-1],"ThrawnTroopers":[-1,-1],"Nute-OR":[-1,-1],"501st":[-1,-1]}},{"name":"CptMaximum","id":"738485185","values":{"Geonosians":[103258,103258],"Nute-Wat":[-1,-1],"Carth":[90701,90701],"FO":[104628,105614],"Clones":[-1,-1],"Wampa (Counter)":[-1,-1],"SionSolo (Counter)":[-1,-1],"Raddus":[-1,-1],"Bad Batch":[127850,127850],"Jawas":[-1,-1],"Wiggs":[-1,-1],"Thragma (Counter)":[-1,-1],"NS":[-1,-1],"EP (Counter, Rebel)":[-1,-1],"padme":[154105,154105],"SEE":[-1,-1],"Disintegration":[-1,-1],"HansMF":[405187,405187],"JKL":[-1,-1],"Executor":[-1,-1],"BH":[121010,121010],"Ewoks":[92368,92368],"GL Rey":[-1,-1],"Maul":[-1,-1],"NestSolo (Counter)":[20911,20911],"zMaul":[-1,-1],"NestSisters":[-1,-1],"Traya":[134247,134247],"CLS":[136020,136020],"QiraNest":[-1,-1],"Troopers":[130949,130949],"JTR":[114531,114531],"JMK":[-1,-1],"NS_Alt":[101085,101085],"Executrix":[414515,414960],"Revan Offense":[-1,-1],"JMLS":[169386,169386],"Grievous-Wat":[-1,-1],"Malevolence":[-1,-1],"Phasma":[-1,-1],"GAS":[-1,-1],"Mon Mothma":[104708,104708],"BS":[130475,130475],"Grievous":[123980,123980],"Qira":[-1,-1],"ShaakClones":[148981,148981],"Phoenix":[74705,74705],"SL Kylo":[-1,-1],"zEP":[-1,-1],"Negotiator":[505638,505638],"Rogue1":[73080,73080],"Iden Troopers":[103877,103877],"DRMalak":[119366,119366],"DR":[-1,-1],"ThrawnTroopers":[-1,-1],"Nute-OR":[-1,-1],"501st":[-1,-1]}},{"name":"Kruggosvet","id":"775667646","values":{"Geonosians":[92818,93300],"Nute-Wat":[-1,-1],"Carth":[105826,105826],"FO":[98964,98964],"Clones":[-1,-1],"Wampa (Counter)":[-1,-1],"SionSolo (Counter)":[-1,-1],"Raddus":[-1,-1],"Bad Batch":[-1,-1],"Jawas":[81029,81029],"Wiggs":[96157,96157],"Thragma (Counter)":[-1,-1],"NS":[-1,-1],"EP (Counter, Rebel)":[-1,-1],"padme":[145284,145284],"SEE":[-1,-1],"Disintegration":[-1,-1],"HansMF":[445904,445904],"JKL":[-1,-1],"Executor":[-1,-1],"BH":[130388,130388],"Ewoks":[87512,87512],"GL Rey":[-1,-1],"Maul":[-1,-1],"NestSolo (Counter)":[19848,19848],"zMaul":[-1,-1],"NestSisters":[-1,-1],"Traya":[121637,121637],"CLS":[131991,131991],"QiraNest":[-1,-1],"Troopers":[69499,69499],"JTR":[-1,-1],"JMK":[-1,-1],"NS_Alt":[-1,-1],"Executrix":[-1,-1],"Revan Offense":[144181,144391],"JMLS":[-1,-1],"Grievous-Wat":[-1,-1],"Malevolence":[-1,-1],"Phasma":[-1,-1],"GAS":[137765,138736],"Mon Mothma":[-1,-1],"BS":[-1,-1],"Grievous":[130491,131402],"Qira":[-1,-1],"ShaakClones":[-1,-1],"Phoenix":[97279,97279],"SL Kylo":[-1,-1],"zEP":[-1,-1],"Negotiator":[504258,504258],"Rogue1":[92159,92159],"Iden Troopers":[-1,-1],"DRMalak":[124151,124151],"DR":[-1,-1],"ThrawnTroopers":[-1,-1],"Nute-OR":[-1,-1],"501st":[-1,-1]}},{"name":"Lefter","id":"817836618","values":{"Geonosians":[94321,94321],"Nute-Wat":[-1,-1],"Carth":[88249,88249],"FO":[-1,-1],"Clones":[-1,-1],"Wampa (Counter)":[-1,-1],"SionSolo (Counter)":[19197,19197],"Raddus":[-1,-1],"Bad Batch":[-1,-1],"Jawas":[60355,60355],"Wiggs":[-1,-1],"Thragma (Counter)":[-1,-1],"NS":[93686,93686],"EP (Counter, Rebel)":[-1,-1],"padme":[136816,136816],"SEE":[-1,-1],"Disintegration":[-1,-1],"HansMF":[383023,383023],"JKL":[-1,-1],"Executor":[-1,-1],"BH":[110889,110889],"Ewoks":[90498,90498],"GL Rey":[161875,161875],"Maul":[-1,-1],"NestSolo (Counter)":[18636,18636],"zMaul":[-1,-1],"NestSisters":[-1,-1],"Traya":[-1,-1],"CLS":[120219,120219],"QiraNest":[-1,-1],"Troopers":[89371,89371],"JTR":[-1,-1],"JMK":[-1,-1],"NS_Alt":[-1,-1],"Executrix":[392317,392317],"Revan Offense":[127833,127833],"JMLS":[-1,-1],"Grievous-Wat":[-1,-1],"Malevolence":[303349,303349],"Phasma":[117284,117284],"GAS":[105377,105377],"Mon Mothma":[89664,89664],"BS":[-1,-1],"Grievous":[119819,119819],"Qira":[-1,-1],"ShaakClones":[-1,-1],"Phoenix":[74926,74926],"SL Kylo":[156090,156090],"zEP":[117671,117671],"Negotiator":[430920,430920],"Rogue1":[-1,-1],"Iden Troopers":[-1,-1],"DRMalak":[118370,118370],"DR":[-1,-1],"ThrawnTroopers":[-1,-1],"Nute-OR":[-1,-1],"501st":[-1,-1]}},{"name":"The Exile","id":"857332717","values":{"Geonosians":[-1,-1],"Nute-Wat":[-1,-1],"Carth":[122730,122730],"FO":[-1,-1],"Clones":[-1,-1],"Wampa (Counter)":[-1,-1],"SionSolo (Counter)":[-1,-1],"Raddus":[-1,-1],"Bad Batch":[45746,45746],"Jawas":[-1,-1],"Wiggs":[98647,98647],"Thragma (Counter)":[-1,-1],"NS":[81651,81651],"EP (Counter, Rebel)":[-1,-1],"padme":[-1,-1],"SEE":[-1,-1],"Disintegration":[-1,-1],"HansMF":[404557,404557],"JKL":[-1,-1],"Executor":[-1,-1],"BH":[127083,127083],"Ewoks":[85334,85334],"GL Rey":[161216,161216],"Maul":[-1,-1],"NestSolo (Counter)":[-1,-1],"zMaul":[97642,97642],"NestSisters":[-1,-1],"Traya":[138622,138622],"CLS":[140594,140594],"QiraNest":[69797,69797],"Troopers":[-1,-1],"JTR":[-1,-1],"JMK":[167115,167115],"NS_Alt":[-1,-1],"Executrix":[-1,-1],"Revan Offense":[-1,-1],"JMLS":[-1,-1],"Grievous-Wat":[137156,137156],"Malevolence":[-1,-1],"Phasma":[64052,64052],"GAS":[143271,143271],"Mon Mothma":[92655,92655],"BS":[-1,-1],"Grievous":[-1,-1],"Qira":[-1,-1],"ShaakClones":[-1,-1],"Phoenix":[93599,93599],"SL Kylo":[-1,-1],"zEP":[-1,-1],"Negotiator":[494523,494523],"Rogue1":[59220,59220],"Iden Troopers":[63605,63605],"DRMalak":[155226,155226],"DR":[-1,-1],"ThrawnTroopers":[-1,-1],"Nute-OR":[-1,-1],"501st":[-1,-1]}},{"name":"Saxmo","id":"922466947","values":{"Geonosians":[95011,95011],"Nute-Wat":[-1,-1],"Carth":[83652,83652],"FO":[-1,125436],"Clones":[-1,-1],"Wampa (Counter)":[-1,-1],"SionSolo (Counter)":[-1,-1],"Raddus":[-1,-1],"Bad Batch":[-1,-1],"Jawas":[43058,43058],"Wiggs":[-1,-1],"Thragma (Counter)":[-1,-1],"NS":[-1,-1],"EP (Counter, Rebel)":[-1,-1],"padme":[131124,131124],"SEE":[-1,-1],"Disintegration":[-1,-1],"HansMF":[359940,360305],"JKL":[-1,-1],"Executor":[-1,-1],"BH":[119084,119084],"Ewoks":[84910,84910],"GL Rey":[-1,-1],"Maul":[-1,-1],"NestSolo (Counter)":[-1,-1],"zMaul":[-1,-1],"NestSisters":[103673,103673],"Traya":[125880,125880],"CLS":[115955,115955],"QiraNest":[-1,-1],"Troopers":[62124,62124],"JTR":[-1,-1],"JMK":[-1,-1],"NS_Alt":[-1,-1],"Executrix":[366672,371476],"Revan Offense":[147105,147105],"JMLS":[-1,-1],"Grievous-Wat":[-1,-1],"Malevolence":[276711,276711],"Phasma":[-1,128840],"GAS":[118950,118950],"Mon Mothma":[74574,74805],"BS":[-1,-1],"Grievous":[135119,135119],"Qira":[-1,-1],"ShaakClones":[-1,-1],"Phoenix":[70044,70044],"SL Kylo":[-1,-1],"zEP":[-1,-1],"Negotiator":[481826,481826],"Rogue1":[-1,-1],"Iden Troopers":[-1,-1],"DRMalak":[110648,110648],"DR":[-1,-1],"ThrawnTroopers":[-1,-1],"Nute-OR":[-1,-1],"501st":[-1,-1]}},{"name":"Dark Helmut","id":"922689332","values":{"Geonosians":[117465,117465],"Nute-Wat":[-1,-1],"Carth":[-1,-1],"FO":[114885,114885],"Clones":[-1,-1],"Wampa (Counter)":[-1,-1],"SionSolo (Counter)":[-1,-1],"Raddus":[-1,-1],"Bad Batch":[81138,81138],"Jawas":[72559,72559],"Wiggs":[-1,-1],"Thragma (Counter)":[-1,-1],"NS":[107601,107601],"EP (Counter, Rebel)":[-1,-1],"padme":[144099,144099],"SEE":[-1,-1],"Disintegration":[-1,-1],"HansMF":[453443,453443],"JKL":[-1,-1],"Executor":[-1,-1],"BH":[110713,110713],"Ewoks":[85580,85580],"GL Rey":[-1,-1],"Maul":[-1,-1],"NestSolo (Counter)":[-1,-1],"zMaul":[98763,98763],"NestSisters":[-1,-1],"Traya":[125590,125590],"CLS":[150335,150335],"QiraNest":[-1,-1],"Troopers":[99709,99709],"JTR":[-1,-1],"JMK":[-1,-1],"NS_Alt":[-1,-1],"Executrix":[428766,428766],"Revan Offense":[-1,-1],"JMLS":[164862,164862],"Grievous-Wat":[-1,-1],"Malevolence":[327900,327900],"Phasma":[-1,-1],"GAS":[-1,-1],"Mon Mothma":[106068,106068],"BS":[-1,-1],"Grievous":[122133,122133],"Qira":[93315,93315],"ShaakClones":[134536,134536],"Phoenix":[92971,92971],"SL Kylo":[-1,-1],"zEP":[-1,-1],"Negotiator":[498876,498876],"Rogue1":[-1,-1],"Iden Troopers":[-1,-1],"DRMalak":[128757,128757],"DR":[-1,-1],"ThrawnTroopers":[-1,-1],"Nute-OR":[-1,-1],"501st":[-1,-1]}},{"name":"BootyMaster","id":"941781972","values":{"Geonosians":[87804,87804],"Nute-Wat":[-1,-1],"Carth":[97947,97947],"FO":[-1,-1],"Clones":[-1,-1],"Wampa (Counter)":[-1,-1],"SionSolo (Counter)":[-1,-1],"Raddus":[-1,-1],"Bad Batch":[131710,131710],"Jawas":[70213,70213],"Wiggs":[84552,84552],"Thragma (Counter)":[78498,78498],"NS":[79614,79614],"EP (Counter, Rebel)":[-1,-1],"padme":[136736,136736],"SEE":[-1,-1],"Disintegration":[-1,-1],"HansMF":[372586,372586],"JKL":[-1,-1],"Executor":[-1,-1],"BH":[124446,124446],"Ewoks":[93024,93024],"GL Rey":[-1,-1],"Maul":[-1,-1],"NestSolo (Counter)":[19684,19684],"zMaul":[-1,-1],"NestSisters":[-1,-1],"Traya":[-1,-1],"CLS":[-1,-1],"QiraNest":[-1,-1],"Troopers":[67422,67620],"JTR":[62685,65390],"JMK":[-1,-1],"NS_Alt":[-1,-1],"Executrix":[-1,-1],"Revan Offense":[122825,122825],"JMLS":[-1,-1],"Grievous-Wat":[-1,-1],"Malevolence":[284034,284034],"Phasma":[82635,82635],"GAS":[160382,160382],"Mon Mothma":[66459,66459],"BS":[-1,-1],"Grievous":[132053,132053],"Qira":[-1,-1],"ShaakClones":[-1,-1],"Phoenix":[77755,77755],"SL Kylo":[-1,-1],"zEP":[114593,114593],"Negotiator":[488970,488970],"Rogue1":[-1,-1],"Iden Troopers":[-1,-1],"DRMalak":[109668,109668],"DR":[-1,-1],"ThrawnTroopers":[-1,-1],"Nute-OR":[-1,-1],"501st":[-1,-1]}},{"name":"Artox","id":"944778717","values":{"Geonosians":[96155,96155],"Nute-Wat":[-1,-1],"Carth":[97643,97665],"FO":[90153,90273],"Clones":[-1,-1],"Wampa (Counter)":[-1,-1],"SionSolo (Counter)":[18312,18312],"Raddus":[-1,-1],"Bad Batch":[127117,127117],"Jawas":[71073,71073],"Wiggs":[-1,-1],"Thragma (Counter)":[87206,87206],"NS":[107292,107292],"EP (Counter, Rebel)":[-1,-1],"padme":[146213,146213],"SEE":[-1,-1],"Disintegration":[112341,113157],"HansMF":[422952,422952],"JKL":[-1,-1],"Executor":[-1,-1],"BH":[138716,138716],"Ewoks":[96281,96327],"GL Rey":[162836,162836],"Maul":[-1,-1],"NestSolo (Counter)":[18834,18834],"zMaul":[-1,-1],"NestSisters":[-1,-1],"Traya":[-1,-1],"CLS":[141804,141804],"QiraNest":[-1,-1],"Troopers":[118293,118293],"JTR":[-1,-1],"JMK":[-1,-1],"NS_Alt":[-1,-1],"Executrix":[482794,482831],"Revan Offense":[-1,-1],"JMLS":[168841,168841],"Grievous-Wat":[-1,-1],"Malevolence":[300097,300097],"Phasma":[-1,-1],"GAS":[-1,-1],"Mon Mothma":[106541,106541],"BS":[-1,-1],"Grievous":[127793,127793],"Qira":[-1,-1],"ShaakClones":[131579,131579],"Phoenix":[86666,86666],"SL Kylo":[-1,-1],"zEP":[129668,129685],"Negotiator":[455796,455796],"Rogue1":[-1,-1],"Iden Troopers":[-1,-1],"DRMalak":[123140,123140],"DR":[-1,-1],"ThrawnTroopers":[-1,-1],"Nute-OR":[-1,-1],"501st":[-1,-1]}},{"name":"DarthBuckyLasek","id":"949196553","values":{"Geonosians":[-1,-1],"Nute-Wat":[-1,-1],"Carth":[-1,-1],"FO":[-1,-1],"Clones":[-1,-1],"Wampa (Counter)":[-1,-1],"SionSolo (Counter)":[13563,13563],"Raddus":[-1,-1],"Bad Batch":[-1,-1],"Jawas":[-1,-1],"Wiggs":[-1,-1],"Thragma (Counter)":[-1,-1],"NS":[82965,84743],"EP (Counter, Rebel)":[-1,-1],"padme":[121421,121421],"SEE":[-1,-1],"Disintegration":[-1,-1],"HansMF":[387481,387481],"JKL":[-1,-1],"Executor":[-1,-1],"BH":[99914,99914],"Ewoks":[81028,81028],"GL Rey":[-1,-1],"Maul":[-1,-1],"NestSolo (Counter)":[16957,16957],"zMaul":[-1,-1],"NestSisters":[-1,-1],"Traya":[-1,-1],"CLS":[148934,148934],"QiraNest":[-1,-1],"Troopers":[54756,54756],"JTR":[-1,-1],"JMK":[-1,-1],"NS_Alt":[-1,-1],"Executrix":[-1,-1],"Revan Offense":[-1,-1],"JMLS":[-1,-1],"Grievous-Wat":[-1,-1],"Malevolence":[222579,223672],"Phasma":[123974,123974],"GAS":[-1,-1],"Mon Mothma":[107442,107442],"BS":[-1,-1],"Grievous":[109049,111098],"Qira":[-1,-1],"ShaakClones":[100967,100967],"Phoenix":[70169,70169],"SL Kylo":[144549,144549],"zEP":[108608,108608],"Negotiator":[409568,409568],"Rogue1":[-1,-1],"Iden Troopers":[-1,-1],"DRMalak":[-1,-1],"DR":[-1,-1],"ThrawnTroopers":[-1,-1],"Nute-OR":[-1,-1],"501st":[-1,-1]}},{"name":"loverofbooty","id":"965659962","values":{"Geonosians":[117380,117380],"Nute-Wat":[-1,-1],"Carth":[99462,99462],"FO":[-1,-1],"Clones":[-1,-1],"Wampa (Counter)":[-1,-1],"SionSolo (Counter)":[-1,-1],"Raddus":[-1,-1],"Bad Batch":[87530,90665],"Jawas":[83095,83095],"Wiggs":[-1,-1],"Thragma (Counter)":[-1,-1],"NS":[-1,-1],"EP (Counter, Rebel)":[-1,-1],"padme":[146210,146210],"SEE":[-1,-1],"Disintegration":[-1,-1],"HansMF":[411810,411810],"JKL":[-1,-1],"Executor":[-1,-1],"BH":[120346,123078],"Ewoks":[97252,97252],"GL Rey":[-1,-1],"Maul":[-1,-1],"NestSolo (Counter)":[-1,-1],"zMaul":[-1,-1],"NestSisters":[110030,110030],"Traya":[118249,118249],"CLS":[150198,150198],"QiraNest":[-1,-1],"Troopers":[123054,125331],"JTR":[-1,-1],"JMK":[-1,-1],"NS_Alt":[-1,-1],"Executrix":[-1,-1],"Revan Offense":[-1,-1],"JMLS":[167520,167520],"Grievous-Wat":[-1,-1],"Malevolence":[-1,-1],"Phasma":[124295,124295],"GAS":[-1,-1],"Mon Mothma":[119865,119865],"BS":[-1,-1],"Grievous":[127708,127708],"Qira":[-1,-1],"ShaakClones":[149752,149752],"Phoenix":[77427,77427],"SL Kylo":[151677,151677],"zEP":[-1,-1],"Negotiator":[535939,535939],"Rogue1":[77896,77896],"Iden Troopers":[79166,79166],"DRMalak":[126329,126329],"DR":[-1,-1],"ThrawnTroopers":[-1,-1],"Nute-OR":[-1,-1],"501st":[-1,-1]}},{"name":"Zazuking","id":"974279168","values":{"Geonosians":[100125,100125],"Nute-Wat":[-1,-1],"Carth":[-1,-1],"FO":[-1,-1],"Clones":[-1,-1],"Wampa (Counter)":[-1,-1],"SionSolo (Counter)":[20236,20236],"Raddus":[-1,-1],"Bad Batch":[83366,83366],"Jawas":[53375,53375],"Wiggs":[-1,-1],"Thragma (Counter)":[-1,-1],"NS":[-1,-1],"EP (Counter, Rebel)":[-1,-1],"padme":[132566,132566],"SEE":[-1,-1],"Disintegration":[-1,-1],"HansMF":[387171,387697],"JKL":[-1,-1],"Executor":[-1,-1],"BH":[96386,96386],"Ewoks":[90722,90722],"GL Rey":[-1,-1],"Maul":[-1,-1],"NestSolo (Counter)":[18679,18679],"zMaul":[-1,-1],"NestSisters":[-1,-1],"Traya":[-1,-1],"CLS":[128205,132683],"QiraNest":[-1,-1],"Troopers":[71972,71972],"JTR":[-1,-1],"JMK":[-1,-1],"NS_Alt":[80342,80342],"Executrix":[357001,357001],"Revan Offense":[120866,120866],"JMLS":[-1,-1],"Grievous-Wat":[130468,130468],"Malevolence":[296814,296814],"Phasma":[117558,117558],"GAS":[-1,-1],"Mon Mothma":[104450,104684],"BS":[-1,-1],"Grievous":[-1,-1],"Qira":[-1,-1],"ShaakClones":[145107,145107],"Phoenix":[65689,65689],"SL Kylo":[141968,141968],"zEP":[110308,110308],"Negotiator":[440692,440692],"Rogue1":[-1,-1],"Iden Troopers":[69569,69569],"DRMalak":[102983,102983],"DR":[-1,-1],"ThrawnTroopers":[-1,-1],"Nute-OR":[99427,99427],"501st":[-1,-1]}},{"name":"Brezenski","id":"984531628","values":{"Geonosians":[104351,104351],"Nute-Wat":[-1,-1],"Carth":[88718,88718],"FO":[85092,85092],"Clones":[-1,-1],"Wampa (Counter)":[-1,-1],"SionSolo (Counter)":[14100,14100],"Raddus":[-1,-1],"Bad Batch":[85775,86536],"Jawas":[90436,90436],"Wiggs":[-1,-1],"Thragma (Counter)":[90137,90137],"NS":[105700,105793],"EP (Counter, Rebel)":[-1,-1],"padme":[144455,144455],"SEE":[-1,-1],"Disintegration":[106024,106057],"HansMF":[406194,406194],"JKL":[-1,-1],"Executor":[-1,-1],"BH":[113266,113313],"Ewoks":[87789,87789],"GL Rey":[-1,-1],"Maul":[-1,-1],"NestSolo (Counter)":[-1,-1],"zMaul":[109785,111759],"NestSisters":[-1,-1],"Traya":[-1,-1],"CLS":[150073,150073],"QiraNest":[66970,66970],"Troopers":[82194,82194],"JTR":[-1,-1],"JMK":[-1,-1],"NS_Alt":[-1,-1],"Executrix":[414753,414753],"Revan Offense":[-1,-1],"JMLS":[170937,170937],"Grievous-Wat":[-1,-1],"Malevolence":[319764,319764],"Phasma":[-1,-1],"GAS":[-1,-1],"Mon Mothma":[113446,113446],"BS":[-1,-1],"Grievous":[140268,140268],"Qira":[-1,-1],"ShaakClones":[139557,139557],"Phoenix":[75817,75817],"SL Kylo":[-1,-1],"zEP":[128928,128928],"Negotiator":[481886,481886],"Rogue1":[62876,62876],"Iden Troopers":[-1,-1],"DRMalak":[135956,135956],"DR":[-1,-1],"ThrawnTroopers":[-1,-1],"Nute-OR":[-1,-1],"501st":[-1,-1]}},{"name":"LordGiygas","id":"989758934","values":{"Geonosians":[96586,96586],"Nute-Wat":[-1,-1],"Carth":[93943,93943],"FO":[-1,-1],"Clones":[-1,-1],"Wampa (Counter)":[-1,-1],"SionSolo (Counter)":[-1,-1],"Raddus":[-1,-1],"Bad Batch":[-1,-1],"Jawas":[-1,-1],"Wiggs":[-1,-1],"Thragma (Counter)":[-1,-1],"NS":[68811,68811],"EP (Counter, Rebel)":[-1,-1],"padme":[-1,-1],"SEE":[160965,161175],"Disintegration":[-1,-1],"HansMF":[279716,279716],"JKL":[-1,-1],"Executor":[-1,-1],"BH":[136038,136038],"Ewoks":[-1,-1],"GL Rey":[-1,-1],"Maul":[-1,-1],"NestSolo (Counter)":[-1,-1],"zMaul":[95429,95429],"NestSisters":[-1,-1],"Traya":[122380,122380],"CLS":[84066,84066],"QiraNest":[-1,-1],"Troopers":[128346,128346],"JTR":[-1,-1],"JMK":[-1,-1],"NS_Alt":[-1,-1],"Executrix":[-1,-1],"Revan Offense":[122554,122554],"JMLS":[-1,-1],"Grievous-Wat":[-1,-1],"Malevolence":[294077,294077],"Phasma":[-1,-1],"GAS":[-1,-1],"Mon Mothma":[-1,-1],"BS":[-1,-1],"Grievous":[100817,100817],"Qira":[-1,-1],"ShaakClones":[87112,87112],"Phoenix":[68972,68972],"SL Kylo":[-1,-1],"zEP":[-1,-1],"Negotiator":[-1,-1],"Rogue1":[-1,-1],"Iden Troopers":[79732,79732],"DRMalak":[-1,-1],"DR":[-1,-1],"ThrawnTroopers":[-1,-1],"Nute-OR":[-1,-1],"501st":[-1,-1]}}]}