{"y":"gp","dates":["09\/19\/2022"],"series":[{"name":"Quigonlot","id":"134378465","values":{"toons":[3473933],"total":[5482457],"ships":[2008524]}},{"name":"Amon Wádde","id":"153929289","values":{"toons":[2935131],"total":[4899035],"ships":[1963904]}},{"name":"SozBoss","id":"161171655","values":{"toons":[2780823],"total":[4723488],"ships":[1942665]}},{"name":"Georgalas","id":"163845417","values":{"toons":[3469045],"total":[5655749],"ships":[2186704]}},{"name":"Hersh Bathens","id":"169344771","values":{"toons":[3094019],"total":[5041938],"ships":[1947919]}},{"name":"TheOld Wookie9","id":"233978862","values":{"toons":[2415851],"total":[4344968],"ships":[1929117]}},{"name":"Caducus ''DM''","id":"254666175","values":{"toons":[2879238],"total":[5169806],"ships":[2290568]}},{"name":"Ichnar","id":"262513128","values":{"toons":[2684992],"total":[4341291],"ships":[1656299]}},{"name":"Rastaban Bromwen","id":"285928752","values":{"toons":[3977383],"total":[6500375],"ships":[2522992]}},{"name":"jpark786","id":"297614349","values":{"toons":[2808623],"total":[4616120],"ships":[1807497]}},{"name":"Furious Siths","id":"362547244","values":{"toons":[3054673],"total":[5287473],"ships":[2232800]}},{"name":"Joezeppy","id":"379494365","values":{"toons":[2942655],"total":[5314223],"ships":[2371568]}},{"name":"MINI Bakku","id":"382239855","values":{"toons":[2487727],"total":[4134571],"ships":[1646844]}},{"name":"Cassian Andor Buttbecause","id":"394779766","values":{"toons":[3723913],"total":[6403940],"ships":[2680027]}},{"name":"MINI Bonnie","id":"417645749","values":{"ships":[3281312],"total":[7690748],"toons":[4409436]}},{"name":"Mr lazy dude","id":"418462675","values":{"ships":[1767393],"total":[4585207],"toons":[2817814]}},{"name":"Jáy Savo","id":"462733628","values":{"ships":[2150177],"total":[5276826],"toons":[3126649]}},{"name":"LEWI5","id":"468549553","values":{"ships":[1749792],"total":[4315124],"toons":[2565332]}},{"name":"Jek Porkins","id":"474918489","values":{"ships":[2197178],"total":[5155421],"toons":[2958243]}},{"name":"Rogmeister","id":"483476373","values":{"ships":[2443097],"total":[6003452],"toons":[3560355]}},{"name":"Balg","id":"512565482","values":{"toons":[2397588],"total":[4146126],"ships":[1748538]}},{"name":"Apolji","id":"514485923","values":{"toons":[1758729],"total":[2958362],"ships":[1199633]}},{"name":"AK47","id":"524931148","values":{"total":[6251024],"toons":[3702939],"ships":[2548085]}},{"name":"Verzun","id":"525592558","values":{"toons":[2016766],"ships":[1314838],"total":[3331604]}},{"name":"Alburreg78","id":"535986745","values":{"toons":[2485678],"total":[4589081],"ships":[2103403]}},{"name":"LaZJC","id":"557128958","values":{"total":[5648043],"toons":[3261607],"ships":[2386436]}},{"name":"MINI Palithimus","id":"578692728","values":{"toons":[4277012],"ships":[2976599],"total":[7253611]}},{"name":"DizzyDees","id":"586975163","values":{"toons":[2915664],"ships":[2468778],"total":[5384442]}},{"name":"Shadows Print","id":"614373377","values":{"toons":[2234970],"ships":[1481981],"total":[3716951]}},{"name":"Jägermeister","id":"616452763","values":{"toons":[2904883],"ships":[2084870],"total":[4989753]}},{"name":"Fishku","id":"639366169","values":{"toons":[3320162],"ships":[2859292],"total":[6179454]}},{"name":"Twoslot","id":"653564588","values":{"toons":[3426059],"ships":[2348488],"total":[5774547]}},{"name":"MINI Tycho Amat","id":"657515741","values":{"toons":[3593573],"ships":[2754357],"total":[6347930]}},{"name":"Judge Judy","id":"659372944","values":{"toons":[2524420],"ships":[2156274],"total":[4680694]}},{"name":"SWAS6640","id":"677126217","values":{"toons":[3033034],"ships":[2372880],"total":[5405914]}},{"name":"Hurnt","id":"763699921","values":{"toons":[3595292],"ships":[2719637],"total":[6314929]}},{"name":"Aurainsoph","id":"782322485","values":{"toons":[3953061],"ships":[2986058],"total":[6939119]}},{"name":"Ben Swolo","id":"782972867","values":{"toons":[3959943],"ships":[2930169],"total":[6890112]}},{"name":"Loather","id":"784731388","values":{"toons":[3675012],"ships":[2847913],"total":[6522925]}},{"name":"Gmosabi β 0296 on Discord","id":"824369415","values":{"toons":[4426825],"ships":[3198080],"total":[7624905]}},{"name":"LordMongoose","id":"837186221","values":{"toons":[4095785],"ships":[2720167],"total":[6815952]}},{"name":"Gondor Man","id":"867248522","values":{"toons":[3530529],"ships":[2637192],"total":[6167721]}},{"name":"ΞSteelWheelzΞ","id":"879812164","values":{"toons":[4356743],"ships":[3377406],"total":[7734149]}},{"name":"DarthRey","id":"899417886","values":{"total":[4378510],"toons":[2650969],"ships":[1727541]}},{"name":"Fango Jett","id":"929411876","values":{"toons":[2611429],"total":[4304179],"ships":[1692750]}},{"name":"Wanbawkenobi","id":"942195748","values":{"toons":[3801606],"ships":[2800699],"total":[6602305]}},{"name":"Dendra McLunkey Partol","id":"958836711","values":{"total":[6934349],"toons":[4017544],"ships":[2916805]}}]}